{"title":"Combined feed","url":"https://MOVIECORD.github.io/maxmovie/all.xml","elements":[{"title":"undefined (맥스무비)","contents":"<a href=\"/movies\" style=\"color:#222\" class=\"EachMenu__NavHref-sc-9yn4xi-6 dOAOeY\">영화</a>","retrieved":1717063718606},{"title":"undefined (맥스무비)","contents":"<a href=\"/peoples\" style=\"color:#222\" class=\"EachMenu__NavHref-sc-9yn4xi-6 dOAOeY\">피플</a>","retrieved":1717063718608},{"title":"undefined (맥스무비)","contents":"<a href=\"/series\" style=\"color:#222\" class=\"EachMenu__NavHref-sc-9yn4xi-6 dOAOeY\">시리즈</a>","retrieved":1717063718609},{"title":"undefined (맥스무비)","contents":"<a href=\"/moviereview\" style=\"color:#222\" class=\"EachMenu__NavHref-sc-9yn4xi-6 dOAOeY\">영화 리뷰</a>","retrieved":1717063718611},{"title":"undefined (맥스무비)","contents":"<a href=\"/seriesreview\" style=\"color:#222\" class=\"EachMenu__NavHref-sc-9yn4xi-6 dOAOeY\">시리즈 리뷰</a>","retrieved":1717063718612},{"title":"undefined (맥스무비)","contents":"<a href=\"/event\" style=\"color:#222\" class=\"EachMenu__NavHref-sc-9yn4xi-6 dOAOeY\">시사회·이벤트</a>","retrieved":1717063718615},{"title":"undefined (맥스무비)","contents":"<a href=\"/eventResult\" style=\"color:#222\" class=\"EachMenu__NavHref-sc-9yn4xi-6 dOAOeY\">당첨자 발표</a>","retrieved":1717063718649},{"title":"undefined (맥스무비)","contents":"<a href=\"/photo\" style=\"color:#222\" class=\"EachMenu__NavHref-sc-9yn4xi-6 dOAOeY\">포토</a>","retrieved":1717063718653},{"title":"undefined (맥스무비)","contents":"<a href=\"/youtube\" style=\"color:#222\" class=\"EachMenu__NavHref-sc-9yn4xi-6 dOAOeY\">영상</a>","retrieved":1717063718653},{"title":"변우석 보려고 거주지까지 침입…\"성숙한 팬덤 문화\" 당부 (맥스무비)","contents":"\"아티스트 사생활 침해받는 상황\" 법적 조치 경고","link":"https://www.maxmovie.com/news/438096","retrieved":1717060109945,"image":"https://d3ihz389yobwks.cloudfront.net/1717036721792uuWC9.jpg"},{"title":"김준수 무대인사 뜬다, 공연 실황 영화 직접 소개 (맥스무비)","contents":"지난달 개최 콘서트의 실황 6월5일 개봉\n6월5일과 9일 상영관 찾아 관객과 만남","link":"https://www.maxmovie.com/news/438095","retrieved":1717038506248,"image":"https://d3ihz389yobwks.cloudfront.net/1717035136469LbGES.jpg"},{"title":"'모아나2' 온다...새로운 모험·아름다운 바다와 함께 (맥스무비)","contents":"2016년 개봉한 모험 영화 '모아나' 속편\n티저 예고편 공개 8시간 만에 200만 회","link":"https://www.maxmovie.com/news/438088","retrieved":1717060109950,"image":"https://d3ihz389yobwks.cloudfront.net/1717014672787WfVBI.jpg"},{"title":"설경구·김희애의 세 번째 만남 '돌풍'... 대통령 시해 그 후 (맥스무비)","contents":"영화 '더 문' '보통의 가족' 이어 재회 \n넷플릭스 12부작 시리즈 6월28일 공개","link":"https://www.maxmovie.com/news/438093","retrieved":1717035884917,"image":"https://d3ihz389yobwks.cloudfront.net/1717032483934oqmrr.jpg"},{"title":"[데일리 핫이슈] 김호중 KBS 한시적 출연 정지·허광한 사상 검증 압박에 곤혹·유재석 만난 천우희 (맥스무비)","contents":"전날 일어난 엔터테인먼트 이슈를 소개합니다","link":"https://www.maxmovie.com/news/438085","retrieved":1717060109954,"image":"https://d3ihz389yobwks.cloudfront.net/1716982718147FGVnW.jpg"},{"title":"류준열·천우희 '더 에이트 쇼' 넷플릭스 비영어 1위 등극 (맥스무비)","contents":"480만 시청수 기록…68개국 TOP 10 등극","link":"https://www.maxmovie.com/news/438087","retrieved":1717052942674,"image":"https://d3ihz389yobwks.cloudfront.net/1716972365817KZRvQ.jpg"},{"title":"'선재 업고 튀어' 엔플라잉 제이던, 아쉬움 뚝뚝 (맥스무비)","contents":"변우석 절친 겸 이클립스 리더 역\n\"그룹 리더로, 배우로 성장하겠다\"","link":"https://www.maxmovie.com/news/438084","retrieved":1717060109958,"image":"https://d3ihz389yobwks.cloudfront.net/1716965378817ggMED.jpg"},{"title":"변우석 \"'선재 업고 튀어'는 꿈같은 작품, 나에게 온 선재에 고마워\" (맥스무비)","contents":"'선재 업고 튀어' 통해 첫 타이틀롤 도전\n\"1년 동안 선재로 살아, 마음 싱숭생숭\"","link":"https://www.maxmovie.com/news/438083","retrieved":1717060109959,"image":"https://d3ihz389yobwks.cloudfront.net/1716971452744ZjtCM.jpg"},{"title":"'문화가 있는 날'에 개봉하는 강동원 영화의 운명은 (맥스무비)","contents":"'설계자' 영화값 할인하는 마지막 수요일 개봉\n'범죄도시4' 첫날 82만명 동원, 대작 중심 선호","link":"https://www.maxmovie.com/news/438078","retrieved":1717020422329,"image":"https://d3ihz389yobwks.cloudfront.net/1716949684624iSVkP.jpg"},{"title":"'심야식당' 감독이 선사할 위안...'일초 앞, 일초 뒤' 기대되는 이유 (맥스무비)","contents":"야마시타 노부히로, 일본 대표 힐링 감독\n지난해 부산국제영화제에서 상영돼 호평","link":"https://www.maxmovie.com/news/438077","retrieved":1717056650696,"image":"https://d3ihz389yobwks.cloudfront.net/1716961767507u1Lwg.jpg"},{"title":"변우석 끝내 울게 만든 '선재 업고 튀어', 자체 최고 시청률로 거둔 '유종의 미' (맥스무비)","contents":"시청률 5.8%로 자체 최고 기록 경신\n'선재' 신드롬, 인터뷰 등 작품 밖으로 이어간다","link":"https://www.maxmovie.com/news/438076","retrieved":1717060109963,"image":"https://d3ihz389yobwks.cloudfront.net/1716942999521yY2Zn.png"},{"title":"내년 공개 '북극성' 전지현·강동원 맡은 역할은 (맥스무비)","contents":"전지현은 외교관, 강동원은 용병 출신\n강동원 제작에도 참여…디즈니+ 공개","link":"https://www.maxmovie.com/news/438075","retrieved":1717060109964,"image":"https://d3ihz389yobwks.cloudfront.net/1716943243945ln1q4.jpg"},{"title":"'선재' 떠난 변우석, 이제 극장에서 만날 시간 (맥스무비)","contents":"주연 영화 '소울메이트' 재상영\n변우석 신드롬 극장으로 확산","link":"https://www.maxmovie.com/news/438073","retrieved":1717038506257,"image":"https://d3ihz389yobwks.cloudfront.net/1716904462436YulHq.jpg"},{"title":"'인사이드 아웃2'가 '불안'이라는 감정을 메인으로 내세운 이유 (맥스무비)","contents":"불안, 당황, 따분, 부럽의 새 감정 등장\n\"청소년이 된다는 건, 리모델링 공사\"","link":"https://www.maxmovie.com/news/438072","retrieved":1717060109967,"image":"https://d3ihz389yobwks.cloudfront.net/171688495934228JhY.jpg"},{"title":"이종석, 강동원 동료 됐다...'설계자'에서 어떤 모습 보여줄까 (맥스무비)","contents":"극중 강동원의 동료 짝눈 역할로 특별출연\n이종석 롤모델로 강동원 꼽기도, 모델 출신","link":"https://www.maxmovie.com/news/438071","retrieved":1717060109968,"image":"https://d3ihz389yobwks.cloudfront.net/1716881174909LTnXp.jpg"},{"title":"[데일리 핫이슈] 김지원 데뷔 첫 아시아 투어, 김호중 공연 강행 125억원 때문 외 (맥스무비)","contents":"전날 일어난 엔터테인먼트 이슈를 소개합니다","link":"https://www.maxmovie.com/news/438070","retrieved":1717052942698,"image":"https://d3ihz389yobwks.cloudfront.net/1716880356943Pvrhh.jpg"},{"title":"'퓨리오사', 예상 밖 부진...美 '가필드' 韓 '설계자'에 발목 잡히나 (맥스무비)","contents":"북미 주말 1위, 전작에 못 미치는 수익\n한국은 '설계자'가 실시간 예매율 1위","link":"https://www.maxmovie.com/news/438069","retrieved":1717060109981,"image":"https://d3ihz389yobwks.cloudfront.net/1716876261242tIYiZ.jpg"},{"title":"undefined (맥스무비 ─ OTT)","contents":"<a href=\"/movies\" style=\"color:#222\" class=\"EachMenu__NavHref-sc-9yn4xi-6 dOAOeY\">영화</a>","retrieved":1717063745235},{"title":"undefined (맥스무비 ─ OTT)","contents":"<a href=\"/peoples\" style=\"color:#222\" class=\"EachMenu__NavHref-sc-9yn4xi-6 dOAOeY\">피플</a>","retrieved":1717063745237},{"title":"undefined (맥스무비 ─ OTT)","contents":"<a href=\"/series\" style=\"color:#222\" class=\"EachMenu__NavHref-sc-9yn4xi-6 dOAOeY\">시리즈</a>","retrieved":1717063745238},{"title":"undefined (맥스무비 ─ OTT)","contents":"<a href=\"/moviereview\" style=\"color:#222\" class=\"EachMenu__NavHref-sc-9yn4xi-6 dOAOeY\">영화 리뷰</a>","retrieved":1717063745240},{"title":"undefined (맥스무비 ─ OTT)","contents":"<a href=\"/seriesreview\" style=\"color:#222\" class=\"EachMenu__NavHref-sc-9yn4xi-6 dOAOeY\">시리즈 리뷰</a>","retrieved":1717063745241},{"title":"undefined (맥스무비 ─ OTT)","contents":"<a href=\"/event\" style=\"color:#222\" class=\"EachMenu__NavHref-sc-9yn4xi-6 dOAOeY\">시사회·이벤트</a>","retrieved":1717063745243},{"title":"undefined (맥스무비 ─ OTT)","contents":"<a href=\"/eventResult\" style=\"color:#222\" class=\"EachMenu__NavHref-sc-9yn4xi-6 dOAOeY\">당첨자 발표</a>","retrieved":1717063745244},{"title":"undefined (맥스무비 ─ OTT)","contents":"<a href=\"/photo\" style=\"color:#222\" class=\"EachMenu__NavHref-sc-9yn4xi-6 dOAOeY\">포토</a>","retrieved":1717063745245},{"title":"undefined (맥스무비 ─ OTT)","contents":"<a href=\"/youtube\" style=\"color:#222\" class=\"EachMenu__NavHref-sc-9yn4xi-6 dOAOeY\">영상</a>","retrieved":1717063745252},{"title":"박서준 美 데뷔작 '더 마블스', 이제 방구석 1열로 (맥스무비 ─ OTT)","contents":"2월7일 디즈니+ 공개","link":"https://www.maxmovie.com/news/436291","retrieved":1716199709313,"image":"https://d3ihz389yobwks.cloudfront.net/1706000461547Fcisu.jpg"},{"title":"'킬러들의 쇼핑몰', 마침내 드러난 S급 킬러 민혜의 정체 (맥스무비 ─ OTT)","contents":"금해나, S급 킬러로 고난도 액션 선사\n'킬러들의 쇼핑몰', '무빙' 이을까","link":"https://www.maxmovie.com/news/436289","retrieved":1716199709314,"image":"https://d3ihz389yobwks.cloudfront.net/1705994006025n8tKU.jpg"},{"title":"[인터뷰] 첫 욕설 연기 도전 김현주 \"'선산', 폭발할 수 있어서 좋았죠\" (맥스무비 ─ OTT)","contents":"'선산'에서 지질하면서 욕망 품은 역할 소화해\n'지옥' '정이'에 이어 연상호 감독과 세 번째 호흡","link":"https://www.maxmovie.com/news/436285","retrieved":1716199709315,"image":"https://d3ihz389yobwks.cloudfront.net/1705983175793aQDJN.jpg"},{"title":"예사롭지 않은 인기 '킬러들의 쇼핑몰'...액션→서사 휘몰아친다 (맥스무비 ─ OTT)","contents":"1, 2회 공개 이후 한국, 대만, 홍콩 등 1위\n이동욱과 악연 얽힌 조한선 등장 기대","link":"https://www.maxmovie.com/news/436269","retrieved":1715267315404,"image":"https://d3ihz389yobwks.cloudfront.net/1705898783736FLKmt.jpg"},{"title":"주성치·오맹달 잇는 이성민·이희준? '핸섬가이즈' 도대체 어떤 영화? (맥스무비 ─ 포토)","contents":"<a href=\"/news/438094\"><span class=\"imgBox\"><img src=\"https://d3ihz389yobwks.cloudfront.net/1717034787428Gvq6Y.jpg\" alt=\"\"></span><span class=\"textBox\"><h4>주성치·오맹달 잇는 이성민·이희준? '핸섬가이즈' 도대체 어떤 영화? </h4></span></a>","link":"https://www.maxmovie.com/news/438094","retrieved":1717049464353,"image":"https://d3ihz389yobwks.cloudfront.net/1717034787428Gvq6Y.jpg"},{"title":"'대치동 스캔들' 휘말린 안소희 (맥스무비 ─ 포토)","contents":"<a href=\"/news/438092\"><span class=\"imgBox\"><img src=\"https://d3ihz389yobwks.cloudfront.net/1717032711766ONAUl.jpg\" alt=\"\"></span><span class=\"textBox\"><h4>'대치동 스캔들' 휘말린 안소희</h4></span></a>","link":"https://www.maxmovie.com/news/438092","retrieved":1717045710132,"image":"https://d3ihz389yobwks.cloudfront.net/1717032711766ONAUl.jpg"},{"title":"'탈주' 이제훈 쫓는 구교환... 어떤 사연이길래 (맥스무비 ─ 포토)","contents":"<a href=\"/news/438091\"><span class=\"imgBox\"><img src=\"https://d3ihz389yobwks.cloudfront.net/1717031089640aJ8Qz.jpg\" alt=\"\"></span><span class=\"textBox\"><h4>'탈주' 이제훈 쫓는 구교환... 어떤 사연이길래</h4></span></a>","link":"https://www.maxmovie.com/news/438091","retrieved":1717034003987,"image":"https://d3ihz389yobwks.cloudfront.net/1717031089640aJ8Qz.jpg"},{"title":"도파민 터지는 하이틴 스캔들 '하이라키' (맥스무비 ─ 포토)","contents":"<a href=\"/news/438081\"><span class=\"imgBox\"><img src=\"https://d3ihz389yobwks.cloudfront.net/1716959956766qtuYg.jpg\" alt=\"\"></span><span class=\"textBox\"><h4>도파민 터지는 하이틴 스캔들 '하이라키'</h4></span></a>","link":"https://www.maxmovie.com/news/438081","retrieved":1716963053029,"image":"https://d3ihz389yobwks.cloudfront.net/1716959956766qtuYg.jpg"},{"title":"영화도 숏폼처럼... 손석구의 신작 '밤낚시' (맥스무비 ─ 포토)","contents":"<a href=\"/news/438080\"><span class=\"imgBox\"><img src=\"https://d3ihz389yobwks.cloudfront.net/1716958645391sqHh6.jpg\" alt=\"\"></span><span class=\"textBox\"><h4>영화도 숏폼처럼... 손석구의 신작 '밤낚시'</h4></span></a>","link":"https://www.maxmovie.com/news/438080","retrieved":1716959376476,"image":"https://d3ihz389yobwks.cloudfront.net/1716958645391sqHh6.jpg"},{"title":"'탈주' 이제훈, 이번엔 북한 병사다! (맥스무비 ─ 포토)","contents":"<a href=\"/news/438079\"><span class=\"imgBox\"><img src=\"https://d3ihz389yobwks.cloudfront.net/1716951724632mrVzy.jpg\" alt=\"\"></span><span class=\"textBox\"><h4>'탈주' 이제훈, 이번엔 북한 병사다!</h4></span></a>","link":"https://www.maxmovie.com/news/438079","retrieved":1716952150192,"image":"https://d3ihz389yobwks.cloudfront.net/1716951724632mrVzy.jpg"},{"title":"디즈니+로 돌아온 북산고 농구부의 도전... '더 퍼스트 슬램덩크' (맥스무비 ─ 포토)","contents":"<a href=\"/news/438063\"><span class=\"imgBox\"><img src=\"https://d3ihz389yobwks.cloudfront.net/1716861590042TkhuR.jpg\" alt=\"\"></span><span class=\"textBox\"><h4>디즈니+로 돌아온 북산고 농구부의 도전... '더 퍼스트 슬램덩크'</h4></span></a>","link":"https://www.maxmovie.com/news/438063","retrieved":1716865756054,"image":"https://d3ihz389yobwks.cloudfront.net/1716861590042TkhuR.jpg"},{"title":"\"사랑과 증오의 씨앗\" 시고니 위버의  새 얼굴, 영화 '마스터 가드너' (맥스무비 ─ 포토)","contents":"<a href=\"/news/438062\"><span class=\"imgBox\"><img src=\"https://d3ihz389yobwks.cloudfront.net/1716860059839mpnLv.jpg\" alt=\"\"></span><span class=\"textBox\"><h4>\"사랑과 증오의 씨앗\" 시고니 위버의  새 얼굴, 영화 '마스터 가드너' </h4></span></a>","link":"https://www.maxmovie.com/news/438062","retrieved":1716872888638,"image":"https://d3ihz389yobwks.cloudfront.net/1716860059839mpnLv.jpg"},{"title":"냉탕 온탕 오가는 '원더랜드' 박보검의 두 얼굴 (맥스무비 ─ 포토)","contents":"<a href=\"/news/438061\"><span class=\"imgBox\"><img src=\"https://d3ihz389yobwks.cloudfront.net/1716857774866p2niJ.jpg\" alt=\"\"></span><span class=\"textBox\"><h4>냉탕 온탕 오가는 '원더랜드' 박보검의 두 얼굴</h4></span></a>","link":"https://www.maxmovie.com/news/438061","retrieved":1716861121008,"image":"https://d3ihz389yobwks.cloudfront.net/1716857774866p2niJ.jpg"},{"title":"송강호부터 변요한까지... '삼식이 삼촌' 촬영장 비하인드 (맥스무비 ─ 포토)","contents":"<a href=\"/news/438050\"><span class=\"imgBox\"><img src=\"https://d3ihz389yobwks.cloudfront.net/1716776798501lO2xg.jpg\" alt=\"\"></span><span class=\"textBox\"><h4>송강호부터 변요한까지... '삼식이 삼촌' 촬영장 비하인드</h4></span></a>","link":"https://www.maxmovie.com/news/438050","retrieved":1716779424782,"image":"https://d3ihz389yobwks.cloudfront.net/1716776798501lO2xg.jpg"},{"title":"'주온' 감독이 쓴 '기괴도', 초여름에 찾아오는 공포 (맥스무비 ─ 포토)","contents":"<a href=\"/news/438049\"><span class=\"imgBox\"><img src=\"https://d3ihz389yobwks.cloudfront.net/1716774947587imv7Z.jpg\" alt=\"\"></span><span class=\"textBox\"><h4>'주온' 감독이 쓴 '기괴도', 초여름에 찾아오는 공포 </h4></span></a>","link":"https://www.maxmovie.com/news/438049","retrieved":1716790298945,"image":"https://d3ihz389yobwks.cloudfront.net/1716774947587imv7Z.jpg"},{"title":"덱스와 조여정의 만남, 영화 '타로' 어떤 이야기? (맥스무비 ─ 포토)","contents":"<a href=\"/news/438047\"><span class=\"imgBox\"><img src=\"https://d3ihz389yobwks.cloudfront.net/1716772085731FwD5C.jpg\" alt=\"\"></span><span class=\"textBox\"><h4>덱스와 조여정의 만남, 영화 '타로' 어떤 이야기?</h4></span></a>","link":"https://www.maxmovie.com/news/438047","retrieved":1716774761680,"image":"https://d3ihz389yobwks.cloudfront.net/1716772085731FwD5C.jpg"},{"title":"칸 영화제 누빈, '베테랑2' 황정민·정해인·류승완 감독...현장 포착 (맥스무비 ─ 포토)","contents":"<a href=\"/news/438027\"><span class=\"imgBox\"><img src=\"https://d3ihz389yobwks.cloudfront.net/1716538208255URk6U.jpg\" alt=\"\"></span><span class=\"textBox\"><h4>칸 영화제 누빈, '베테랑2' 황정민·정해인·류승완 감독...현장 포착</h4></span></a>","link":"https://www.maxmovie.com/news/438027","retrieved":1716545270950,"image":"https://d3ihz389yobwks.cloudfront.net/1716538208255URk6U.jpg"},{"title":"지브리 애니 작화 감독의 신작 '북극백화점의 안내원' (맥스무비 ─ 포토)","contents":"<a href=\"/news/438017\"><span class=\"imgBox\"><img src=\"https://d3ihz389yobwks.cloudfront.net/17165191559287WS2T.jpg\" alt=\"\"></span><span class=\"textBox\"><h4>지브리 애니 작화 감독의 신작 '북극백화점의 안내원'</h4></span></a>","link":"https://www.maxmovie.com/news/438017","retrieved":1716523788301,"image":"https://d3ihz389yobwks.cloudfront.net/17165191559287WS2T.jpg"},{"title":"변요한·신혜선의 '그녀가 죽었다'... 촬영 현장 엿보니 (맥스무비 ─ 포토)","contents":"<a href=\"/news/438014\"><span class=\"imgBox\"><img src=\"https://d3ihz389yobwks.cloudfront.net/1716514773226wAeLT.jpg\" alt=\"\"></span><span class=\"textBox\"><h4>변요한·신혜선의 '그녀가 죽었다'... 촬영 현장 엿보니 </h4></span></a>","link":"https://www.maxmovie.com/news/438014","retrieved":1716517415403,"image":"https://d3ihz389yobwks.cloudfront.net/1716514773226wAeLT.jpg"},{"title":"'맑광눈' 천우희의 하드캐리, '더 에이트 쇼' 촬영 현장 비하인드 (맥스무비 ─ 포토)","contents":"<a href=\"/news/438013\"><span class=\"imgBox\"><img src=\"https://d3ihz389yobwks.cloudfront.net/1716512546646AnO1Y.jpg\" alt=\"\"></span><span class=\"textBox\"><h4>'맑광눈' 천우희의 하드캐리, '더 에이트 쇼' 촬영 현장 비하인드 </h4></span></a>","link":"https://www.maxmovie.com/news/438013","retrieved":1716515406522,"image":"https://d3ihz389yobwks.cloudfront.net/1716512546646AnO1Y.jpg"},{"title":"거짓말로 무너진 어른, 거짓말로 살아난 아이...영화 '양치기' (맥스무비 ─ 포토)","contents":"<a href=\"/news/438001\"><span class=\"imgBox\"><img src=\"https://d3ihz389yobwks.cloudfront.net/17164310078186Quzd.jpg\" alt=\"\"></span><span class=\"textBox\"><h4>거짓말로 무너진 어른, 거짓말로 살아난 아이...영화 '양치기' </h4></span></a>","link":"https://www.maxmovie.com/news/438001","retrieved":1716441020129,"image":"https://d3ihz389yobwks.cloudfront.net/17164310078186Quzd.jpg"},{"title":"승무원 커플 수지·박보검, '원더랜드' 호흡 엿보니... (맥스무비 ─ 포토)","contents":"<a href=\"/news/438000\"><span class=\"imgBox\"><img src=\"https://d3ihz389yobwks.cloudfront.net/171642824575266Ndt.jpg\" alt=\"\"></span><span class=\"textBox\"><h4>승무원 커플 수지·박보검, '원더랜드' 호흡 엿보니...</h4></span></a>","link":"https://www.maxmovie.com/news/438000","retrieved":1716430963046,"image":"https://d3ihz389yobwks.cloudfront.net/171642824575266Ndt.jpg"},{"title":"박해일의 목소리로 전하는 '판문점'의 의미 (맥스무비 ─ 포토)","contents":"<a href=\"/news/437999\"><span class=\"imgBox\"><img src=\"https://d3ihz389yobwks.cloudfront.net/1716427240600Jn6S9.png\" alt=\"\"></span><span class=\"textBox\"><h4>박해일의 목소리로 전하는 '판문점'의 의미</h4></span></a>","link":"https://www.maxmovie.com/news/437999","retrieved":1716428848379,"image":"https://d3ihz389yobwks.cloudfront.net/1716427240600Jn6S9.png"},{"title":"'인사이드 아웃2'도 피할 수 없는, 무서운 사춘기 (맥스무비 ─ 포토)","contents":"<a href=\"/news/437991\"><span class=\"imgBox\"><img src=\"https://d3ihz389yobwks.cloudfront.net/1716355108216pvyk1.jpg\" alt=\"\"></span><span class=\"textBox\"><h4>'인사이드 아웃2'도 피할 수 없는, 무서운 사춘기 </h4></span></a>","link":"https://www.maxmovie.com/news/437991","retrieved":1716358270850,"image":"https://d3ihz389yobwks.cloudfront.net/1716355108216pvyk1.jpg"},{"title":"인기 유튜버 박주현, 트렁크에 갇힌 이유는? 영화 '드라이브' (맥스무비 ─ 포토)","contents":"<a href=\"/news/437984\"><span class=\"imgBox\"><img src=\"https://d3ihz389yobwks.cloudfront.net/17163419945977vUjK.jpg\" alt=\"\"></span><span class=\"textBox\"><h4>인기 유튜버 박주현, 트렁크에 갇힌 이유는? 영화 '드라이브' &nbsp;</h4></span></a>","link":"https://www.maxmovie.com/news/437984","retrieved":1716344606669,"image":"https://d3ihz389yobwks.cloudfront.net/17163419945977vUjK.jpg"},{"title":"하정우‧여진구의 비행기 납치 실화, '하이재킹' 관객 사로잡을까 (맥스무비 ─ 포토)","contents":"<a href=\"/news/437982\"><span class=\"imgBox\"><img src=\"https://d3ihz389yobwks.cloudfront.net/1716340421353Jy3II.jpg\" alt=\"\"></span><span class=\"textBox\"><h4>하정우‧여진구의 비행기 납치 실화, '하이재킹' 관객 사로잡을까</h4></span></a>","link":"https://www.maxmovie.com/news/437982","retrieved":1716342530329,"image":"https://d3ihz389yobwks.cloudfront.net/1716340421353Jy3II.jpg"},{"title":"윌 스미스·마틴 로렌스가 돌아왔다! '나쁜 녀석들: 라이드 오어 다이' (맥스무비 ─ 포토)","contents":"<a href=\"/news/437965\"><span class=\"imgBox\"><img src=\"https://d3ihz389yobwks.cloudfront.net/1716260082301td4bH.jpg\" alt=\"\"></span><span class=\"textBox\"><h4>윌 스미스·마틴 로렌스가 돌아왔다! '나쁜 녀석들: 라이드 오어 다이'</h4></span></a>","link":"https://www.maxmovie.com/news/437965","retrieved":1716260923541,"image":"https://d3ihz389yobwks.cloudfront.net/1716260082301td4bH.jpg"},{"title":"상위 0.01% 고등학교 '하이라키', 베일 벗는 하이틴 스캔들 (맥스무비 ─ 포토)","contents":"<a href=\"/news/437963\"><span class=\"imgBox\"><img src=\"https://d3ihz389yobwks.cloudfront.net/1716257781457Z5QSi.jpg\" alt=\"\"></span><span class=\"textBox\"><h4>상위 0.01% 고등학교 '하이라키', 베일 벗는 하이틴 스캔들 </h4></span></a>","link":"https://www.maxmovie.com/news/437963","retrieved":1716260923541,"image":"https://d3ihz389yobwks.cloudfront.net/1716257781457Z5QSi.jpg"},{"title":"김준수 콘서트 실황 영화, 드디어 온다! (맥스무비 ─ 포토)","contents":"<a href=\"/news/437961\"><span class=\"imgBox\"><img src=\"https://d3ihz389yobwks.cloudfront.net/1716255856341xJyDK.jpg\" alt=\"\"></span><span class=\"textBox\"><h4>김준수 콘서트 실황 영화, 드디어 온다! </h4></span></a>","link":"https://www.maxmovie.com/news/437961","retrieved":1716258208379,"image":"https://d3ihz389yobwks.cloudfront.net/1716255856341xJyDK.jpg"},{"title":"충격적 페티시 담은 영화 '정욕'... 올바른 욕망이란? (맥스무비 ─ 포토)","contents":"<a href=\"/news/437950\"><span class=\"imgBox\"><img src=\"https://d3ihz389yobwks.cloudfront.net/1716186614197UZOlC.jpg\" alt=\"\"></span><span class=\"textBox\"><h4>충격적 페티시 담은 영화 '정욕'... 올바른 욕망이란?</h4></span></a>","link":"https://www.maxmovie.com/news/437950","retrieved":1716188920308,"image":"https://d3ihz389yobwks.cloudfront.net/1716186614197UZOlC.jpg"},{"title":"위대한 예술가 라파엘로의 삶, 영화 '라파엘로. 예술의 군주' 미리 봤더니 (맥스무비 ─ 포토)","contents":"<a href=\"/news/437946\"><span class=\"imgBox\"><img src=\"https://d3ihz389yobwks.cloudfront.net/1716171303128EQZBt.jpg\" alt=\"\"></span><span class=\"textBox\"><h4>위대한 예술가 라파엘로의 삶, 영화 '라파엘로. 예술의 군주' 미리 봤더니</h4></span></a>","link":"https://www.maxmovie.com/news/437946","retrieved":1716174556440,"image":"https://d3ihz389yobwks.cloudfront.net/1716171303128EQZBt.jpg"},{"title":"'트리플 천만' 일군 '범죄도시4'의 생생한 촬영현장 비하인드 (맥스무비 ─ 포토)","contents":"<a href=\"/news/437945\"><span class=\"imgBox\"><img src=\"https://d3ihz389yobwks.cloudfront.net/1716169418833VRkIo.jpg\" alt=\"\"></span><span class=\"textBox\"><h4>'트리플 천만' 일군 '범죄도시4'의 생생한 촬영현장 비하인드 </h4></span></a>","link":"https://www.maxmovie.com/news/437945","retrieved":1716171875024,"image":"https://d3ihz389yobwks.cloudfront.net/1716169418833VRkIo.jpg"},{"title":"엘비스 프레슬리의 유일한 사랑... 영화 '프리실라' (맥스무비 ─ 포토)","contents":"<a href=\"/news/437908\"><span class=\"imgBox\"><img src=\"https://d3ihz389yobwks.cloudfront.net/1715917036977OMbPL.jpg\" alt=\"\"></span><span class=\"textBox\"><h4>엘비스 프레슬리의 유일한 사랑... 영화 '프리실라'</h4></span></a>","link":"https://www.maxmovie.com/news/437908","retrieved":1715929734152,"image":"https://d3ihz389yobwks.cloudfront.net/1715917036977OMbPL.jpg"},{"title":"너드걸의 청춘·성장·사랑...영화 '마거리트의 정리' (맥스무비 ─ 포토)","contents":"<a href=\"/news/437907\"><span class=\"imgBox\"><img src=\"https://d3ihz389yobwks.cloudfront.net/1715911420741iBdiG.jpg\" alt=\"\"></span><span class=\"textBox\"><h4>너드걸의 청춘·성장·사랑...영화 '마거리트의 정리'</h4></span></a>","link":"https://www.maxmovie.com/news/437907","retrieved":1715915327220,"image":"https://d3ihz389yobwks.cloudfront.net/1715911420741iBdiG.jpg"}]}