{"title":"Combined feed","url":"https://MOVIECORD.github.io/maxmovie/all.xml","elements":[{"title":"undefined (맥스무비)","contents":"<a href=\"/movies\" style=\"color:#222\" class=\"EachMenu__NavHref-sc-9yn4xi-6 dOAOeY\">영화</a>","retrieved":1737619949538},{"title":"undefined (맥스무비)","contents":"<a href=\"/peoples\" style=\"color:#222\" class=\"EachMenu__NavHref-sc-9yn4xi-6 dOAOeY\">피플</a>","retrieved":1737619949539},{"title":"undefined (맥스무비)","contents":"<a href=\"/series\" style=\"color:#222\" class=\"EachMenu__NavHref-sc-9yn4xi-6 dOAOeY\">시리즈</a>","retrieved":1737619949539},{"title":"undefined (맥스무비)","contents":"<a href=\"/moviereview\" style=\"color:#222\" class=\"EachMenu__NavHref-sc-9yn4xi-6 dOAOeY\">영화 리뷰</a>","retrieved":1737619949539},{"title":"undefined (맥스무비)","contents":"<a href=\"/seriesreview\" style=\"color:#222\" class=\"EachMenu__NavHref-sc-9yn4xi-6 dOAOeY\">시리즈 리뷰</a>","retrieved":1737619949540},{"title":"undefined (맥스무비)","contents":"<a href=\"/event\" style=\"color:#222\" class=\"EachMenu__NavHref-sc-9yn4xi-6 dOAOeY\">시사회·이벤트</a>","retrieved":1737619949540},{"title":"undefined (맥스무비)","contents":"<a href=\"/eventResult\" style=\"color:#222\" class=\"EachMenu__NavHref-sc-9yn4xi-6 dOAOeY\">당첨자 발표</a>","retrieved":1737619949540},{"title":"undefined (맥스무비)","contents":"<a href=\"/photo\" style=\"color:#222\" class=\"EachMenu__NavHref-sc-9yn4xi-6 dOAOeY\">포토</a>","retrieved":1737619949541},{"title":"undefined (맥스무비)","contents":"<a href=\"/youtube\" style=\"color:#222\" class=\"EachMenu__NavHref-sc-9yn4xi-6 dOAOeY\">영상</a>","retrieved":1737619949541},{"title":"'히트맨2' 첫날 10만 동원...개봉일 반짝 효과? (맥스무비)","contents":"1편 코미디 강점 살리지 못한 아쉬움 \n24일 '검은 수녀들' 개봉 후 본격 경쟁","link":"https://www.maxmovie.com/news/441297","retrieved":1737612761830,"image":"https://d3ihz389yobwks.cloudfront.net/1737591549621C7uYd.jpg"},{"title":"[인터뷰] 도경수에게 사랑이란...\"소중함\" (맥스무비)","contents":"27일 개봉 '말할 수 없는 비밀' 주연\n\"성숙한 멜로, 원작과 비교해 강점\"","link":"https://www.maxmovie.com/news/441292","retrieved":1737612761833,"image":"https://d3ihz389yobwks.cloudfront.net/1737535637210teTut.jpg"},{"title":"영화 '소방관' 설 앞두고 IPTV 공개...이제 안방에서 본다 (맥스무비)","contents":"23일&nbsp;IPTV 및 VOD 서비스 시작\n소방관들의 희생 다룬 실화 소재","link":"https://www.maxmovie.com/news/441299","retrieved":1737612761835,"image":"https://d3ihz389yobwks.cloudfront.net/1737595561419yfivg.jpg"},{"title":"개봉하는 유아인 주연 영화 '승부', 리스크 어떻게 넘을까 (맥스무비)","contents":"'소방관' 배급사 맡아 극장 개봉 추진\n살아있는 '바둑 천재'의 실화 이야기","link":"https://www.maxmovie.com/news/441296","retrieved":1737616121166,"image":"https://d3ihz389yobwks.cloudfront.net/17376006422137Igwk.jpg"},{"title":"그래서 닥터 트리거는 누구? '트리거'가 풀어낼 이야기 살펴보니 (맥스무비)","contents":"카타르시스 안긴 탐사보도 PD들의 이야기\n고양이 연쇄 살인사건 \"한도의 변화 결심\"","link":"https://www.maxmovie.com/news/441293","retrieved":1737616121167,"image":"https://d3ihz389yobwks.cloudfront.net/17375239032432JUmT.jpg"},{"title":"도경수·원진아→진영·다현, 로맨스 바람 일으킬까 (맥스무비)","contents":"동명의 대만 인기 로맨스 리메이크\n원작 명성, 팬덤 등에 업고 관객 공략","link":"https://www.maxmovie.com/news/441295","retrieved":1737616121168,"image":"https://d3ihz389yobwks.cloudfront.net/1737532405194pV2Xn.jpg"},{"title":"'나의 완벽한 비서' 이준혁·한지민만큼 궁금한 김도훈·김윤혜 (맥스무비)","contents":"가슴 저릿한 짝사랑하는 정훈과 수현\n\"아버님\"으로 시작된 인연, 사랑될까","link":"https://www.maxmovie.com/news/441289","retrieved":1737616121169,"image":"https://d3ihz389yobwks.cloudfront.net/1737524416386a4O0k.jpg"},{"title":"손석구·최희서, 미국 독립영화 주연..할리우드로 (맥스무비)","contents":"올해 봄 촬영하는 '베드포드 파크' 출연\n2014년 연극 이후 네 번째 호흡도 눈길","link":"https://www.maxmovie.com/news/441291","retrieved":1737616121169,"image":"https://d3ihz389yobwks.cloudfront.net/1737520773547Q82ON.jpg"},{"title":"'미키17' 봉준호의 차기작? \"비주얼에 매혹된 심해생물\" (맥스무비)","contents":"해양 생물과 인간 관계 그린 첫 장편 애니\n제작비 700억원 한국영화 역대 최고 규모","link":"https://www.maxmovie.com/news/441285","retrieved":1737616121171,"image":"https://d3ihz389yobwks.cloudfront.net/1737509643857ziBEf.jpg"},{"title":"이준혁, 로맨스 남주 벗는다...신혜선 쫓는 강력계 형사 변신 (맥스무비)","contents":"넷플릭스 새 오리지널 시리즈 '레이디 두아'\n이준혁·신혜선 '비밀의 숲' 이후 두 번째 호흡","link":"https://www.maxmovie.com/news/441286","retrieved":1737616121172,"image":"https://d3ihz389yobwks.cloudfront.net/1737506943950zdxCB.jpg"},{"title":"권상우의 '히트맨2' 출격…설 극장전 서막 올랐다 (맥스무비)","contents":"지각변동 예고, 전편 등에 업고 흥행 할까\n이틀 뒤엔 '검은 수녀들' '귀신경찰' 출격","link":"https://www.maxmovie.com/news/441287","retrieved":1737616121172,"image":"https://d3ihz389yobwks.cloudfront.net/1737509630036NucYg.jpg"},{"title":"또 베를린 초청 홍상수​‧김민희의 '그 자연이 네게 뭐라고 하니' 어떤 이야기? (맥스무비)","contents":"2020년부터 매년 베를린 국제영화제 초청  \n연인의 집 우연히 찾은 30대 시인의 이야기","link":"https://www.maxmovie.com/news/441284","retrieved":1737616121173,"image":"https://d3ihz389yobwks.cloudfront.net/1737472936458urvYo.jpg"},{"title":"'검은 수녀들'과 '트리거' 관통하는 두 얼굴, 10대 문우진의 도약 (맥스무비)","contents":"표현하기 어려운 캐릭터 잇단 도전 \n'검은 수녀들'에서 악령에 씐 소년 \n'트리거'에서 양면성 지닌 캐릭터","link":"https://www.maxmovie.com/news/441280","retrieved":1737616121174,"image":"https://d3ihz389yobwks.cloudfront.net/1737447144626E7qNT.jpg"},{"title":"[리뷰: 포테이토 지수 81%] '아수라처럼' 고레에다 감독이 포착한 '가족의 균열' (맥스무비)","contents":"'어느 가족'·'괴물' 감독의 7부작 드라마 \n아버지의 불륜 알게 된 네 자매 이야기","link":"https://www.maxmovie.com/news/441277","retrieved":1737616121175,"image":"https://d3ihz389yobwks.cloudfront.net/1737449282910wkGa8.jpg"},{"title":"홍상수 '그 자연이 네게 뭐라고 하니' 베를린영화제 경쟁 부문 초청 (맥스무비)","contents":"홍상수 6년 연속 베를린국제영화제 초청\n민규동 '파과'·봉준호 '미키17' 등도 상영","link":"https://www.maxmovie.com/news/441283","retrieved":1737616121180,"image":"https://d3ihz389yobwks.cloudfront.net/1737459401014r7J4v.jpg"},{"title":"[인터뷰] 새로운 연기 재미에 눈 뜬 '배우 송혜교' (맥스무비)","contents":"24일 개봉 '검은 수녀들' 유니아 수녀\n인물의 용기와 결단력에 매료돼 선택 \n\"나에게 없는 용기와 대담함에 끌려\"","link":"https://www.maxmovie.com/news/441281","retrieved":1737616121182,"image":"https://d3ihz389yobwks.cloudfront.net/1737448204823BqkQZ.jpg"},{"title":"운명 개척한 임지연, 연진이 넘어 '옥씨부인전'으로 대표작 교체 (맥스무비)","contents":"노비에서 양반으로, 임지연의 맹활약\n사극 드라마 타이틀롤 부담 딛고 성공","link":"https://www.maxmovie.com/news/441278","retrieved":1737616121183,"image":"https://d3ihz389yobwks.cloudfront.net/17374369358417nP2u.jpg"},{"title":"[맥스포토] '중증외상센터' 통쾌한 메디컬 활극 기대만발 (맥스무비 ─ 포토)","contents":"<a href=\"/news/441276\"><span class=\"imgBox\"><img src=\"https://d3ihz389yobwks.cloudfront.net/1737429708547Z5Q1R.png\" alt=\"\"></span><span class=\"textBox\"><h4>[맥스포토] '중증외상센터' 통쾌한 메디컬 활극 기대만발</h4></span></a>","link":"https://www.maxmovie.com/news/441276","retrieved":1737436239541,"image":"https://d3ihz389yobwks.cloudfront.net/1737429708547Z5Q1R.png"},{"title":"[맥스포토] 정재광 '중증외상센터'로 만나요~ (맥스무비 ─ 포토)","contents":"<a href=\"/news/441275\"><span class=\"imgBox\"><img src=\"https://d3ihz389yobwks.cloudfront.net/1737429447877h2dP3.png\" alt=\"\"></span><span class=\"textBox\"><h4>[맥스포토] 정재광 '중증외상센터'로 만나요~</h4></span></a>","link":"https://www.maxmovie.com/news/441275","retrieved":1737436239545,"image":"https://d3ihz389yobwks.cloudfront.net/1737429447877h2dP3.png"},{"title":"[맥스포토] 윤경호·주지훈, 대립하는 관계 (맥스무비 ─ 포토)","contents":"<a href=\"/news/441274\"><span class=\"imgBox\"><img src=\"https://d3ihz389yobwks.cloudfront.net/1737428845841URIeu.png\" alt=\"\"></span><span class=\"textBox\"><h4>[맥스포토] 윤경호·주지훈, 대립하는 관계</h4></span></a>","link":"https://www.maxmovie.com/news/441274","retrieved":1737436239545,"image":"https://d3ihz389yobwks.cloudfront.net/1737428845841URIeu.png"},{"title":"[맥스포토] 하영, 미모의 홍일점 (맥스무비 ─ 포토)","contents":"<a href=\"/news/441272\"><span class=\"imgBox\"><img src=\"https://d3ihz389yobwks.cloudfront.net/1737427511400cIhyC.png\" alt=\"\"></span><span class=\"textBox\"><h4>[맥스포토] 하영, 미모의 홍일점</h4></span></a>","link":"https://www.maxmovie.com/news/441272","retrieved":1737436239545,"image":"https://d3ihz389yobwks.cloudfront.net/1737427511400cIhyC.png"},{"title":"[맥스포토] 추영우, 한복 벗고 의사 변신 (맥스무비 ─ 포토)","contents":"<a href=\"/news/441273\"><span class=\"imgBox\"><img src=\"https://d3ihz389yobwks.cloudfront.net/1737428107383ZXxsx.png\" alt=\"\"></span><span class=\"textBox\"><h4>[맥스포토] 추영우, 한복 벗고 의사 변신</h4></span></a>","link":"https://www.maxmovie.com/news/441273","retrieved":1737436239547,"image":"https://d3ihz389yobwks.cloudfront.net/1737428107383ZXxsx.png"},{"title":"[맥스포토] 새해 첫 오컬트 '검은 수녀들' 주역들 (맥스무비 ─ 포토)","contents":"<a href=\"/news/441262\"><span class=\"imgBox\"><img src=\"https://d3ihz389yobwks.cloudfront.net/1737364218518Ut4IT.png\" alt=\"\"></span><span class=\"textBox\"><h4>[맥스포토] 새해 첫 오컬트 '검은 수녀들' 주역들</h4></span></a>","link":"https://www.maxmovie.com/news/441262","retrieved":1737367872370,"image":"https://d3ihz389yobwks.cloudfront.net/1737364218518Ut4IT.png"},{"title":"[맥스포토] 이진욱·문우진 '검은 수녀들'의 남자들 (맥스무비 ─ 포토)","contents":"<a href=\"/news/441261\"><span class=\"imgBox\"><img src=\"https://d3ihz389yobwks.cloudfront.net/1737362615768KWWnO.png\" alt=\"\"></span><span class=\"textBox\"><h4>[맥스포토] 이진욱·문우진 '검은 수녀들'의 남자들</h4></span></a>","link":"https://www.maxmovie.com/news/441261","retrieved":1737367872372,"image":"https://d3ihz389yobwks.cloudfront.net/1737362615768KWWnO.png"},{"title":"[맥스포토] 전여빈, 긴 생머리 미카엘 수녀로 변신 (맥스무비 ─ 포토)","contents":"<a href=\"/news/441260\"><span class=\"imgBox\"><img src=\"https://d3ihz389yobwks.cloudfront.net/1737361901497gXsLH.png\" alt=\"\"></span><span class=\"textBox\"><h4>[맥스포토] 전여빈, 긴 생머리 미카엘 수녀로 변신</h4></span></a>","link":"https://www.maxmovie.com/news/441260","retrieved":1737364383741,"image":"https://d3ihz389yobwks.cloudfront.net/1737361901497gXsLH.png"},{"title":"[맥스포토] 송혜교 '홍합머리'도 완벽 소화하는 미모 (맥스무비 ─ 포토)","contents":"<a href=\"/news/441259\"><span class=\"imgBox\"><img src=\"https://d3ihz389yobwks.cloudfront.net/1737361217577xXwrx.png\" alt=\"\"></span><span class=\"textBox\"><h4>[맥스포토] 송혜교 '홍합머리'도 완벽 소화하는 미모</h4></span></a>","link":"https://www.maxmovie.com/news/441259","retrieved":1737364383741,"image":"https://d3ihz389yobwks.cloudfront.net/1737361217577xXwrx.png"},{"title":"[맥스포토] 로버트 패틴슨, 봉준호 감독과 함께 첫 내한 (맥스무비 ─ 포토)","contents":"<a href=\"/news/441251\"><span class=\"imgBox\"><img src=\"https://d3ihz389yobwks.cloudfront.net/1737342950941M083O.png\" alt=\"\"></span><span class=\"textBox\"><h4>[맥스포토] 로버트 패틴슨, 봉준호 감독과 함께 첫 내한</h4></span></a>","link":"https://www.maxmovie.com/news/441251","retrieved":1737349875073,"image":"https://d3ihz389yobwks.cloudfront.net/1737342950941M083O.png"},{"title":"[맥스포토] 돌아온 봉준호, '미키 17'로 6년 만에 귀환 (맥스무비 ─ 포토)","contents":"<a href=\"/news/441250\"><span class=\"imgBox\"><img src=\"https://d3ihz389yobwks.cloudfront.net/1737342517263GAHqB.png\" alt=\"\"></span><span class=\"textBox\"><h4>[맥스포토] 돌아온 봉준호, '미키 17'로 6년 만에 귀환</h4></span></a>","link":"https://www.maxmovie.com/news/441250","retrieved":1737349875074,"image":"https://d3ihz389yobwks.cloudfront.net/1737342517263GAHqB.png"},{"title":"[맥스포토] 봉준호·로버트 패틴슨, 기대감 높이는 '손하트' 투 샷 (맥스무비 ─ 포토)","contents":"<a href=\"/news/441249\"><span class=\"imgBox\"><img src=\"https://d3ihz389yobwks.cloudfront.net/1737341242641F22Rz.png\" alt=\"\"></span><span class=\"textBox\"><h4>[맥스포토] 봉준호·로버트 패틴슨, 기대감 높이는 '손하트' 투 샷</h4></span></a>","link":"https://www.maxmovie.com/news/441249","retrieved":1737349875074,"image":"https://d3ihz389yobwks.cloudfront.net/1737341242641F22Rz.png"},{"title":"[맥스포토] 설 연휴 가족과 함께! '히트맨2' 주역들 (맥스무비 ─ 포토)","contents":"<a href=\"/news/441207\"><span class=\"imgBox\"><img src=\"https://d3ihz389yobwks.cloudfront.net/1736932128329WbdJk.png\" alt=\"\"></span><span class=\"textBox\"><h4>[맥스포토] 설 연휴 가족과 함께! '히트맨2' 주역들</h4></span></a>","link":"https://www.maxmovie.com/news/441207","retrieved":1736935809342,"image":"https://d3ihz389yobwks.cloudfront.net/1736932128329WbdJk.png"},{"title":"[맥스포토] 김성오·정준호·이이경, '히트맨2'로 호흡 (맥스무비 ─ 포토)","contents":"<a href=\"/news/441206\"><span class=\"imgBox\"><img src=\"https://d3ihz389yobwks.cloudfront.net/1736931594750vUQOb.png\" alt=\"\"></span><span class=\"textBox\"><h4>[맥스포토] 김성오·정준호·이이경, '히트맨2'로 호흡</h4></span></a>","link":"https://www.maxmovie.com/news/441206","retrieved":1736935809339,"image":"https://d3ihz389yobwks.cloudfront.net/1736931594750vUQOb.png"},{"title":"[맥스포토] 권상우, 돌아온 히트맨! (맥스무비 ─ 포토)","contents":"<a href=\"/news/441205\"><span class=\"imgBox\"><img src=\"https://d3ihz389yobwks.cloudfront.net/1736930804621aw6Mt.png\" alt=\"\"></span><span class=\"textBox\"><h4>[맥스포토] 권상우, 돌아온 히트맨!</h4></span></a>","link":"https://www.maxmovie.com/news/441205","retrieved":1736932193088,"image":"https://d3ihz389yobwks.cloudfront.net/1736930804621aw6Mt.png"},{"title":"[맥스포토] '코믹 여신' 황우슬혜, 독보적인 매력 (맥스무비 ─ 포토)","contents":"<a href=\"/news/441204\"><span class=\"imgBox\"><img src=\"https://d3ihz389yobwks.cloudfront.net/1736927109521OWmwC.png\" alt=\"\"></span><span class=\"textBox\"><h4>[맥스포토] '코믹 여신' 황우슬혜, 독보적인 매력</h4></span></a>","link":"https://www.maxmovie.com/news/441204","retrieved":1736932193101,"image":"https://d3ihz389yobwks.cloudfront.net/1736927109521OWmwC.png"},{"title":"[맥스포토] 설 연휴 공략할 '말할 수 없는 비밀' 주역들 (맥스무비 ─ 포토)","contents":"<a href=\"/news/441188\"><span class=\"imgBox\"><img src=\"https://d3ihz389yobwks.cloudfront.net/1736841644801VtzdS.png\" alt=\"\"></span><span class=\"textBox\"><h4>[맥스포토] 설 연휴 공략할 '말할 수 없는 비밀' 주역들</h4></span></a>","link":"https://www.maxmovie.com/news/441188","retrieved":1736842377769,"image":"https://d3ihz389yobwks.cloudfront.net/1736841644801VtzdS.png"},{"title":"[맥스포토] 사랑에 빠진 도경수·원진아 (맥스무비 ─ 포토)","contents":"<a href=\"/news/441186\"><span class=\"imgBox\"><img src=\"https://d3ihz389yobwks.cloudfront.net/1736841071516vFbrf.png\" alt=\"\"></span><span class=\"textBox\"><h4>[맥스포토] 사랑에 빠진 도경수·원진아 </h4></span></a>","link":"https://www.maxmovie.com/news/441186","retrieved":1736842377771,"image":"https://d3ihz389yobwks.cloudfront.net/1736841071516vFbrf.png"},{"title":"[맥스포토] '스크린 데뷔' 신예은, 음대 여신 미모 (맥스무비 ─ 포토)","contents":"<a href=\"/news/441185\"><span class=\"imgBox\"><img src=\"https://d3ihz389yobwks.cloudfront.net/1736839458781BTHdb.png\" alt=\"\"></span><span class=\"textBox\"><h4>[맥스포토] '스크린 데뷔' 신예은, 음대 여신 미모</h4></span></a>","link":"https://www.maxmovie.com/news/441185","retrieved":1736842377772,"image":"https://d3ihz389yobwks.cloudfront.net/1736839458781BTHdb.png"},{"title":"[맥스포토] 신현준, 김영준 감독과 4번째 작품 함께 (맥스무비 ─ 포토)","contents":"<a href=\"/news/441171\"><span class=\"imgBox\"><img src=\"https://d3ihz389yobwks.cloudfront.net/1736756016113iyXzW.png\" alt=\"\"></span><span class=\"textBox\"><h4>[맥스포토] 신현준, 김영준 감독과 4번째 작품 함께</h4></span></a>","link":"https://www.maxmovie.com/news/441171","retrieved":1736759472465,"image":"https://d3ihz389yobwks.cloudfront.net/1736756016113iyXzW.png"},{"title":"[맥스포토] '귀신경찰' 신현준, 눈물 젖은 포토타임 (맥스무비 ─ 포토)","contents":"<a href=\"/news/441170\"><span class=\"imgBox\"><img src=\"https://d3ihz389yobwks.cloudfront.net/1736754775587XO5fZ.png\" alt=\"\"></span><span class=\"textBox\"><h4>[맥스포토] '귀신경찰' 신현준, 눈물 젖은 포토타임</h4></span></a>","link":"https://www.maxmovie.com/news/441170","retrieved":1736759472465,"image":"https://d3ihz389yobwks.cloudfront.net/1736754775587XO5fZ.png"},{"title":"[맥스포토] 디즈니+ '트리거' 웃음만발 주역들 (맥스무비 ─ 포토)","contents":"<a href=\"/news/441111\"><span class=\"imgBox\"><img src=\"https://d3ihz389yobwks.cloudfront.net/1736306138621aDrBi.png\" alt=\"\"></span><span class=\"textBox\"><h4>[맥스포토] 디즈니+ '트리거' 웃음만발 주역들</h4></span></a>","link":"https://www.maxmovie.com/news/441111","retrieved":1736309511622,"image":"https://d3ihz389yobwks.cloudfront.net/1736306138621aDrBi.png"},{"title":"[맥스포토] 정성일·주종혁, 탐사보도PD로 만났어요! (맥스무비 ─ 포토)","contents":"<a href=\"/news/441109\"><span class=\"imgBox\"><img src=\"https://d3ihz389yobwks.cloudfront.net/1736305310219oRPJ6.png\" alt=\"\"></span><span class=\"textBox\"><h4>[맥스포토] 정성일·주종혁, 탐사보도PD로 만났어요!</h4></span></a>","link":"https://www.maxmovie.com/news/441109","retrieved":1736306093019,"image":"https://d3ihz389yobwks.cloudfront.net/1736305310219oRPJ6.png"},{"title":"[맥스포토] '외쳐 갓혜수!' 김혜수, 프로페셔널한 포토타임 (맥스무비 ─ 포토)","contents":"<a href=\"/news/441107\"><span class=\"imgBox\"><img src=\"https://d3ihz389yobwks.cloudfront.net/1736304387438qdnWQ.png\" alt=\"\"></span><span class=\"textBox\"><h4>[맥스포토] '외쳐 갓혜수!' 김혜수, 프로페셔널한 포토타임</h4></span></a>","link":"https://www.maxmovie.com/news/441107","retrieved":1736306093021,"image":"https://d3ihz389yobwks.cloudfront.net/1736304387438qdnWQ.png"},{"title":"[맥스포토] 좀비와 로맨스의 조화...'뉴토피아' 주역들 (맥스무비 ─ 포토)","contents":"<a href=\"/news/441091\"><span class=\"imgBox\"><img src=\"https://d3ihz389yobwks.cloudfront.net/1736218750831l4ZLv.png\" alt=\"\"></span><span class=\"textBox\"><h4>[맥스포토] 좀비와 로맨스의 조화...'뉴토피아' 주역들</h4></span></a>","link":"https://www.maxmovie.com/news/441091","retrieved":1736219853633,"image":"https://d3ihz389yobwks.cloudfront.net/1736218750831l4ZLv.png"},{"title":"[맥스포토] 박정민·지수, 알콩달콩 '곰신' 커플 (맥스무비 ─ 포토)","contents":"<a href=\"/news/441090\"><span class=\"imgBox\"><img src=\"https://d3ihz389yobwks.cloudfront.net/1736218356073hJBAU.png\" alt=\"\"></span><span class=\"textBox\"><h4>[맥스포토] 박정민·지수, 알콩달콩 '곰신' 커플</h4></span></a>","link":"https://www.maxmovie.com/news/441090","retrieved":1736219853633,"image":"https://d3ihz389yobwks.cloudfront.net/1736218356073hJBAU.png"},{"title":"[맥스포토] 박정민 \"지수가 내 여자친구라니...\" (맥스무비 ─ 포토)","contents":"<a href=\"/news/441087\"><span class=\"imgBox\"><img src=\"https://d3ihz389yobwks.cloudfront.net/1736217925651sOaVR.png\" alt=\"\"></span><span class=\"textBox\"><h4>[맥스포토] 박정민 \"지수가 내 여자친구라니...\"</h4></span></a>","link":"https://www.maxmovie.com/news/441087","retrieved":1736219853641,"image":"https://d3ihz389yobwks.cloudfront.net/1736217925651sOaVR.png"},{"title":"[맥스포토] 블랙핑크 지수, 사랑스러움의 인간화 (맥스무비 ─ 포토)","contents":"<a href=\"/news/441086\"><span class=\"imgBox\"><img src=\"https://d3ihz389yobwks.cloudfront.net/1736217471242pXSqf.png\" alt=\"\"></span><span class=\"textBox\"><h4>[맥스포토] 블랙핑크 지수, 사랑스러움의 인간화</h4></span></a>","link":"https://www.maxmovie.com/news/441086","retrieved":1736219853642,"image":"https://d3ihz389yobwks.cloudfront.net/1736217471242pXSqf.png"},{"title":"[맥스포토] 고 송재림 유작 '폭락'의 주역들 (맥스무비 ─ 포토)","contents":"<a href=\"/news/441081\"><span class=\"imgBox\"><img src=\"https://d3ihz389yobwks.cloudfront.net/1736161027737q7VCj.png\" alt=\"\"></span><span class=\"textBox\"><h4>[맥스포토] 고 송재림 유작 '폭락'의 주역들</h4></span></a>","link":"https://www.maxmovie.com/news/441081","retrieved":1736172613529,"image":"https://d3ihz389yobwks.cloudfront.net/1736161027737q7VCj.png"},{"title":"[맥스포토] 영화 '폭락' 동료들이 눈물로 기억하는 고 송재림 (맥스무비 ─ 포토)","contents":"<a href=\"/news/441080\"><span class=\"imgBox\"><img src=\"https://d3ihz389yobwks.cloudfront.net/1736160564053zZB6j.png\" alt=\"\"></span><span class=\"textBox\"><h4>[맥스포토] 영화 '폭락' 동료들이 눈물로 기억하는 고 송재림</h4></span></a>","link":"https://www.maxmovie.com/news/441080","retrieved":1736172580050,"image":"https://d3ihz389yobwks.cloudfront.net/1736160564053zZB6j.png"}]}