{"title":"맥스무비","url":"https://www.maxmovie.com/","favicon":"https://www.maxmovie.com/favicon.ico","elements":[{"contents":"<a href=\"/movies\" style=\"color:#222\" class=\"EachMenu__NavHref-sc-9yn4xi-6 dOAOeY\">영화</a>","retrieved":1712617658859},{"contents":"<a href=\"/peoples\" style=\"color:#222\" class=\"EachMenu__NavHref-sc-9yn4xi-6 dOAOeY\">피플</a>","retrieved":1712617658869},{"contents":"<a href=\"/series\" style=\"color:#222\" class=\"EachMenu__NavHref-sc-9yn4xi-6 dOAOeY\">시리즈</a>","retrieved":1712617658871},{"contents":"<a href=\"/moviereview\" style=\"color:#222\" class=\"EachMenu__NavHref-sc-9yn4xi-6 dOAOeY\">영화 리뷰</a>","retrieved":1712617658871},{"contents":"<a href=\"/seriesreview\" style=\"color:#222\" class=\"EachMenu__NavHref-sc-9yn4xi-6 dOAOeY\">시리즈 리뷰</a>","retrieved":1712617658874},{"contents":"<a href=\"/event\" style=\"color:#222\" class=\"EachMenu__NavHref-sc-9yn4xi-6 dOAOeY\">시사회·이벤트</a>","retrieved":1712617658907},{"contents":"<a href=\"/eventResult\" style=\"color:#222\" class=\"EachMenu__NavHref-sc-9yn4xi-6 dOAOeY\">당첨자 발표</a>","retrieved":1712617658909},{"contents":"<a href=\"/photo\" style=\"color:#222\" class=\"EachMenu__NavHref-sc-9yn4xi-6 dOAOeY\">포토</a>","retrieved":1712617658911},{"contents":"<a href=\"/youtube\" style=\"color:#222\" class=\"EachMenu__NavHref-sc-9yn4xi-6 dOAOeY\">영상</a>","retrieved":1712617658912},{"title":"['기생수' 1위]  2000억원 들인 '삼체'까지 눌렀다, 인기의 힘은?","contents":"'삼체' '젠틀맨' 각각 2, 3위로 밀어내고 1위 올라 \n드라마 가미한 크리처물, 아시아·남미 먼저 반응","link":"https://www.maxmovie.com/news/437354","retrieved":1712617659034,"image":"https://d3ihz389yobwks.cloudfront.net/1712544030552aV8pJ.jpg"},{"title":"['기생수' 1위] 스다 마사키가 왜 나와? 연상호 감독이 자신한 이유","contents":"공개 동시 넷플릭스 TV쇼 부문 세계 시청 순위 1위\n\"마지막까지 꼭 봐주길\" 감독의 이유 있는 부탁","link":"https://www.maxmovie.com/news/437351","retrieved":1712617659035,"image":"https://d3ihz389yobwks.cloudfront.net/1712541782912Oc5N7.jpg"},{"title":"[오늘 뭘 볼까] 특별한 도굴꾼의 사랑과 모험, 영화 '키메라'","contents":"4월3일 개봉, 칸 국제영화제  경쟁부문 초청작\n특별한 능력 가진 도굴꾼의 기묘한 모험 다뤄","link":"https://www.maxmovie.com/news/437358","retrieved":1712614119131,"image":"https://d3ihz389yobwks.cloudfront.net/1712558318124JgiTs.jpg"},{"title":"1000만 영화 '서울의 봄' vs '파묘' , 백상예술대상 격돌","contents":"제60회 백상예술대상 부문별 후보 발표\n남자 최우수연기상 주역 최대 관심사로","link":"https://www.maxmovie.com/news/437356","retrieved":1712567307809,"image":"https://d3ihz389yobwks.cloudfront.net/17125543381399ceTE.jpg"},{"title":"'쿵푸팬더4'에 달아오르는 관심, 왜?","contents":"개봉 D-2 사전예매 12만장 돌파…전편 2배\n프랜차이즈·가족영화·총선 특수 누릴까","link":"https://www.maxmovie.com/news/437353","retrieved":1712617659037,"image":"https://d3ihz389yobwks.cloudfront.net/1712543616018S013e.jpg"},{"title":"한소희→고윤정, NH농협은행 모델 교체","contents":"한소희 최근 소주 이어 은행 광고모델 계약 종료\nNH 측 \"고윤정의 이미지 브랜드 홍보 효과 기대\"","link":"https://www.maxmovie.com/news/437352","retrieved":1712617659038,"image":"https://d3ihz389yobwks.cloudfront.net/1712542888553sYLdB.jpg"},{"title":"'유미의 세포들 더 무비' 해외서도 통했다, 76개국 선판매","contents":"일본 대만 등 아시아 비롯해 미국 프랑스 등 판매\n웹툰으로 시작해 드라마 이어 영화까지 탄생","link":"https://www.maxmovie.com/news/437349","retrieved":1712540529399,"image":"https://d3ihz389yobwks.cloudfront.net/17125375484678wB6d.jpg"},{"title":"'파묘' 1200만 향해 질주…'댓글부대'는","contents":"'파묘' 뒷심 보여주며 45일간 1위\n'댓글부대' 100만 돌파 가능할까","link":"https://www.maxmovie.com/news/437348","retrieved":1712617659041,"image":"https://d3ihz389yobwks.cloudfront.net/1712537828465kCFje.jpg"},{"title":"송하윤·전종서...학폭 의혹 논란? \"집단주의 문화와 살벌한 교육시스템 탓\"","contents":"미국 시사주간지 타임 스타들의 학폭 논란 보도","link":"https://www.maxmovie.com/news/437345","retrieved":1712617659047,"image":"https://d3ihz389yobwks.cloudfront.net/1712533379295VSNvv.jpg"},{"title":"'최애' 구하러 간다...'선재 업고 튀어', 봄에 찾아온 청량 로맨스","contents":"변우석·김혜윤, 청량미 넘치는 '로코 커플' 예약\n15년의 시공간 뛰어넘는 '타임슬립 구원 로맨스' 표방","link":"https://www.maxmovie.com/news/437344","retrieved":1712617659049,"image":"https://d3ihz389yobwks.cloudfront.net/1712486960559hVrQO.jpg"},{"title":"보아 \"SM과 계약은 2025년까지, 그때까지 최선 다하겠다\"","contents":"\"계약 끝나면 은퇴해도 되겠죠?\"라며 은퇴 암시한 보아\n추측 쏟아지자 \"계약은 2025년 12월31일까지\"","link":"https://www.maxmovie.com/news/437343","retrieved":1712617659049,"image":"https://d3ihz389yobwks.cloudfront.net/1712476528013qM1nv.jpg"},{"title":"'기생수:더 그레이'를 향한 말말말 \"진정한 공생의 가능성 제시\"","contents":"일본 SF 만화 '기생수' 원작으로 해\n\"인상적인 오프닝, 끝까지 볼 거라고 마음먹어\"","link":"https://www.maxmovie.com/news/437342","retrieved":1712617659054,"image":"https://d3ihz389yobwks.cloudfront.net/1712475319312SXdB2.jpg"},{"title":"아이콘 바비·정찬우, 5월 나란히 입대 \"안전 위해 비공개 입소\"","contents":"김진환 이어 바비·정찬우 군 복무 돌입\n\"입소 당일 공식 행사는 진행하지 않아\"","link":"https://www.maxmovie.com/news/437340","retrieved":1712617659055,"image":"https://d3ihz389yobwks.cloudfront.net/1712462485484Uv3uC.jpg"},{"title":"'돈의 얼굴'되는 염혜란, 다큐부터 예능까지 '영역 확장'","contents":"EBS 다큐프라임 '돈의 얼굴'에서 돈의 얼굴 추적해\n김태호 PD 연출, '마이 네임 이즈 가브리엘' 출연","link":"https://www.maxmovie.com/news/437339","retrieved":1712617659056,"image":"https://d3ihz389yobwks.cloudfront.net/1712413620777vpo9A.jpg"},{"title":"스티븐 연이 말하는 봉준호 감독은? \"깊이 파고드는 예술가\"","contents":"'미키17'로 '옥자'에 이어 봉준호와 두 번째 호흡\n\"가장 좋아하는 예술가, 함께할 수 있어 감사해\"","link":"https://www.maxmovie.com/news/437338","retrieved":1712617659057,"image":"https://d3ihz389yobwks.cloudfront.net/1712465384712C4b74.jpg"},{"title":"봄과 함께 찾아온 '남은 인생 10년', 8위→5위","contents":"고마츠 나나와 사카구치 켄타로의 사랑 이야기\n4월3일 재개봉, 박스오피스 8위에서 5위로","link":"https://www.maxmovie.com/news/437337","retrieved":1712617659058,"image":"https://d3ihz389yobwks.cloudfront.net/1712408688439PpKR8.jpg"},{"title":"'거장'과 '명장'의 만남...봉준호, 조지 밀러 '퓨리오사' 지원 사격","contents":"조지 밀러 감독, '퓨리오사' 홍보차 내한\n푸티지 시사회 및 GV 진행, 봉준호 감독 참석","link":"https://www.maxmovie.com/news/437336","retrieved":1712617659060,"image":"https://d3ihz389yobwks.cloudfront.net/1712405467855APIhz.jpg"}]}