{"title":"맥스무비","url":"https://www.maxmovie.com/","favicon":"https://www.maxmovie.com/favicon.ico","elements":[{"title":"김히어라 일진 논란에…'SNL4' 결방 결정","contents":"배우 김히어라가 학폭 논란에 휩싸인 가운데, 그의 출연을 예정한 쿠팡플레이 'SNL코리아 시즌4' 녹화가 취소했다.학폭 의혹에 휩싸인 배우 김히어라. 사진제공=그램엔터테인먼트쿠팡플레이는 6일 \"'SNL코리아 시즌4' 김히어라 편 7일 녹화가 취소됐다\"며 \"이에 따라 9일 방송될 예정이었던 9회는 결방된다\"고 밝혔다.김히어라는 학창 시절 비행 청소년 모임(빅","link":"https://www.maxmovie.com/news/434653","retrieved":1693983898465,"image":"https://d3ihz389yobwks.cloudfront.net/1693979660773GgqVN.png"},{"title":"부국제 개막작 '한국이 싫어서'는 어떤 영화?","contents":"고아성 주연 장강명 동명 소설 원작 \n\"동시대 한국사회 젊은이들의 이야기\"","link":"https://www.maxmovie.com/news/434644","retrieved":1693980513568,"image":"https://d3ihz389yobwks.cloudfront.net/1693907527918Ea4pP.jpg"},{"title":"'무빙' DAY, 드디어 나오는 '하수도 액션'","contents":"괴력의 사나이 류승룡 VS 김성균 대결\n가족을 지키려고 괴물이 된 두 남자","link":"https://www.maxmovie.com/news/434646","retrieved":1693980513549,"image":"https://d3ihz389yobwks.cloudfront.net/1693957635868diVII.jpg"},{"title":"장원영·강다니엘·성한빈, '2023 AAA' MC로 랑데부","contents":"가수 장원영과 강다니엘, 성한빈이 '2023 Asia Artist Awards IN PHILIPPINES'(2023 AAA) MC로 나선다.'2023 AAA' MC로 호흡을 맞추는 장원영 강다니엘 성한빈'2023 AAA' 측은 6일 \"장원영이 3년 연속 'AAA'의 진행을 맡게 됐다\"며 \"장원영과 함께 개성 강한 남성미로 여심을 사로잡는 강다니엘과 풋풋한","link":"https://www.maxmovie.com/news/434651","retrieved":1693976681304,"image":"https://d3ihz389yobwks.cloudfront.net/1693975176727SAbMC.jpg"},{"title":"\"우리에게 설리는 좋은 배우였고 좋은 사람이었다\"","contents":"<span class=\"imgBox  floatLeft\"><a href=\"/news/434648\"><span class=\"imgBox\" style=\"background-image:url(https://d3ihz389yobwks.cloudfront.net/1693959299865LDKFD.jpg);background-size:cover\"></span></a></span><span class=\"textBox floatLeft stickerKey1\"><a href=\"/news/434648\"><h4>\"우리에게 설리는 좋은 배우였고 좋은 사람이었다\" </h4></a><span>8시간 전<!-- --> · <a href=\"/writer/136\">이해리 기자</a></span></span>","link":"https://www.maxmovie.com/news/434648","retrieved":1693960081086,"image":"https://d3ihz389yobwks.cloudfront.net/1693959299865LDKFD.jpg"},{"title":"'AI, 인간적인가 인간의 적인가' 묻는 영화","contents":"'크리에이터' 감독이 밝힌 기획 의도\nAI 로봇 소재 SF블록버스터","link":"https://www.maxmovie.com/news/434647","retrieved":1693960081104,"image":"https://d3ihz389yobwks.cloudfront.net/1693958153071XBWwK.jpg"},{"title":"'무빙' 식을 줄 모르는 인기","contents":"8월 5주차  통합 콘텐츠 랭킹 1위\n이재만 숨은 서사 공개","link":"https://www.maxmovie.com/news/434645","retrieved":1693911814362,"image":"https://d3ihz389yobwks.cloudfront.net/1693908515587FHpI2.jpg"},{"title":"[오늘 뭘 볼까] 한 남자의 거짓된 인생, 영화 '한 남자'","contents":"오늘, 볼만한 작품을 추천합니다.◆ '한 남자''한 남자'의 한 장면. 사진제공=트윈플러스파트너스'한 남자'는 죽은 남편의 이름, 과거 모든 것이 다른 사람의 것이었다는 사실이 밝혀지며 정체가 묘연해진 한 남자 X의 거짓된 인생을 따라가는 추적 미스터리 영화다.변호사 키도는 어느 날 의뢰인 리에로부터 그녀의 죽은 남편인 다이스케의 신원조사를 해달라는 기묘한","link":"https://www.maxmovie.com/news/434638","retrieved":1693951446993,"image":"https://d3ihz389yobwks.cloudfront.net/16938879224297aCB6.jpg"},{"title":"\"초청작 감소\"…BIFF, 송강호·주윤발로 위기 돌파할까","contents":"공식 초청작 242편→209편 \"예산 줄어\"\n송강호 호스트로…저우룬파 아시아영화인상","link":"https://www.maxmovie.com/news/434643","retrieved":1693960081084,"image":"https://d3ihz389yobwks.cloudfront.net/1693956457997Tqhy6.jpg"},{"title":"故 설리 마지막 모습, 부산국제영화제 첫 공개","contents":"<span class=\"imgBox  floatLeft\"><a href=\"/news/434642\"><span class=\"imgBox\" style=\"background-image:url(https://d3ihz389yobwks.cloudfront.net/1693896036241tsaeq.jpg);background-size:cover\"></span></a></span><span class=\"textBox floatLeft stickerKey1\"><a href=\"/news/434642\"><h4>故 설리 마지막 모습, 부산국제영화제 첫 공개</h4></a><span>09월 05일<!-- --> · <a href=\"/writer/137\">박미애 기자</a></span></span>","link":"https://www.maxmovie.com/news/434642","retrieved":1693991133284,"image":"https://d3ihz389yobwks.cloudfront.net/1693896036241tsaeq.jpg"}]}