{"title":"맥스무비","url":"https://www.maxmovie.com/","favicon":"https://www.maxmovie.com/favicon.ico","elements":[{"title":"국가가 떠미는 죽음, 영화  '플랜 75' 감독 내한...어떤 이야기 꺼낼까","contents":"국가가 노인의 죽음을 지원하는 근미래 SF 드라마\n고레에다 히로카즈가 선택한 일본 차기 거장 감독","link":"https://www.maxmovie.com/news/436116","retrieved":1704851451371,"image":"https://d3ihz389yobwks.cloudfront.net/1704847079969LO7Mr.jpg"},{"title":"'외계+인' 2부, 예매율 40% 돌파로 관심 고조…1부 만회하나","contents":"'위시'와 큰 차이로 예매율 앞서\n2부는 김태리·이하늬·진선규 부각","link":"https://www.maxmovie.com/news/436119","retrieved":1704851451372,"image":"https://d3ihz389yobwks.cloudfront.net/1704848174585KmjUf.jpg"},{"title":"건물주 vs 장의사…유해진의 극과 극 변신 예고","contents":"내달 '도그데이즈' '파묘' 2편 개봉\n누적관객 1억명 돌파…흥행 행보 이어가나","link":"https://www.maxmovie.com/news/436107","retrieved":1704794846092,"image":"https://d3ihz389yobwks.cloudfront.net/1704790215418gszqD.jpg"},{"title":"마동석의 새로운 액션 예고 '황야'... '범죄도시'와 얼마나 다를까","contents":"무술감독 허명행의 첫 연출 데뷔작\n'범죄도시' 시리즈의 액션 설계자","link":"https://www.maxmovie.com/news/436111","retrieved":1704856059880,"image":"https://d3ihz389yobwks.cloudfront.net/1704785440091ZIHTe.jpg"},{"title":"배우 이성경, 대학병원에 1억원 기부...\"'김사부' 영향\"","contents":"<span class=\"imgBox  floatLeft\"><a href=\"/news/436121\"><span class=\"imgBox\" style=\"background-image:url(https://d3ihz389yobwks.cloudfront.net/1704850736588fm32G.gif);background-size:cover\"></span></a></span><span class=\"textBox floatLeft stickerKey1\"><a href=\"/news/436121\"><h4>배우 이성경, 대학병원에 1억원 기부...\"'김사부' 영향\"</h4></a><span>3시간 전<!-- --> · <a href=\"/writer/136\">이해리 기자</a></span></span>","link":"https://www.maxmovie.com/news/436121","retrieved":1704851451367,"image":"https://d3ihz389yobwks.cloudfront.net/1704850736588fm32G.gif"},{"title":"[데일리 핫이슈]아유미 결혼 2년만에 임신·에마 스톤 '크루엘라'로 복귀·'이효리의 레드카펫' 시간 변경 외","contents":"전날 일어난 엔터테인먼트 이슈를 소개합니다","link":"https://www.maxmovie.com/news/436115","retrieved":1704837925980,"image":"https://d3ihz389yobwks.cloudfront.net/1704807473852SUnrF.jpg"},{"title":"[오늘 뭘 볼까] 1부 떡밥 회수하러 돌아온 영화 '외계+인' 2부","contents":"'외계+인' 2부의 한 장면. 사진제공=CJ ENM오늘, 볼만한 작품을 추천합니다.◆ '외계+인' 2부영화 '외계+인' 2부는 치열한 신검 쟁탈전 속 숨겨진 비밀이 밝혀지는 가운데 미래로 돌아가 모두를 구하려는 인간과 도사들의 이야기를 그린다.&nbsp;인간의 몸속에 가둬진 외계인 죄수의 탈옥을 막으려다 과거에 갇혀버린 이안(김태리)은 우여곡절 끝에 시간의 문을 열","link":"https://www.maxmovie.com/news/436113","retrieved":1704837926004,"image":"https://d3ihz389yobwks.cloudfront.net/1704786526054jV7B8.jpg"},{"title":"서태지 명곡 '시대유감', 그룹 에스파 버전으로 재탄생","contents":"1996년 음반 사전 심의 폐지 이끈 명곡\n걸그룹의 서태지 노래 리메이크 처음","link":"https://www.maxmovie.com/news/436114","retrieved":1704791239528,"image":"https://d3ihz389yobwks.cloudfront.net/1704787211819TZlcI.jpg"},{"title":"'경성크리처' 파트2가 남긴 여운... 시즌2 향한 궁금증으로","contents":"5일 공개 파트2, 일본 내에서도 반향\n시즌2 1945년에서 현재 서울로 전환","link":"https://www.maxmovie.com/news/436108","retrieved":1704863234420,"image":"https://d3ihz389yobwks.cloudfront.net/1704774714527iXxXq.jpg"},{"title":"고 이선균 사건 진상규명 성명 발표에 영화계 한뜻...'선산' 제발회 일정 조정","contents":"<span class=\"imgBox  floatLeft\"><a href=\"/news/436112\"><span class=\"imgBox\" style=\"background-image:url(https://d3ihz389yobwks.cloudfront.net/1704784721850LbgSF.jpg);background-size:cover\"></span></a></span><span class=\"textBox floatLeft stickerKey1\"><a href=\"/news/436112\"><h4>고 이선균 사건 진상규명 성명 발표에 영화계 한뜻...'선산' 제발회 일정 조정 </h4></a><span>21시간 전<!-- --> · <a href=\"/writer/136\">이해리 기자</a></span></span>","link":"https://www.maxmovie.com/news/436112","retrieved":1704787771249,"image":"https://d3ihz389yobwks.cloudfront.net/1704784721850LbgSF.jpg"}]}