{"title":"맥스무비","url":"https://www.maxmovie.com/","favicon":"https://www.maxmovie.com/favicon.ico","elements":[{"contents":"<a href=\"/movies\" style=\"color:#222\" class=\"EachMenu__NavHref-sc-9yn4xi-6 dOAOeY\">영화</a>","retrieved":1739264968939},{"contents":"<a href=\"/peoples\" style=\"color:#222\" class=\"EachMenu__NavHref-sc-9yn4xi-6 dOAOeY\">피플</a>","retrieved":1739264968940},{"contents":"<a href=\"/series\" style=\"color:#222\" class=\"EachMenu__NavHref-sc-9yn4xi-6 dOAOeY\">시리즈</a>","retrieved":1739264968941},{"contents":"<a href=\"/moviereview\" style=\"color:#222\" class=\"EachMenu__NavHref-sc-9yn4xi-6 dOAOeY\">영화 리뷰</a>","retrieved":1739264968941},{"contents":"<a href=\"/seriesreview\" style=\"color:#222\" class=\"EachMenu__NavHref-sc-9yn4xi-6 dOAOeY\">시리즈 리뷰</a>","retrieved":1739264968942},{"contents":"<a href=\"/event\" style=\"color:#222\" class=\"EachMenu__NavHref-sc-9yn4xi-6 dOAOeY\">시사회·이벤트</a>","retrieved":1739264968942},{"contents":"<a href=\"/eventResult\" style=\"color:#222\" class=\"EachMenu__NavHref-sc-9yn4xi-6 dOAOeY\">당첨자 발표</a>","retrieved":1739264968943},{"contents":"<a href=\"/photo\" style=\"color:#222\" class=\"EachMenu__NavHref-sc-9yn4xi-6 dOAOeY\">포토</a>","retrieved":1739264968952},{"contents":"<a href=\"/youtube\" style=\"color:#222\" class=\"EachMenu__NavHref-sc-9yn4xi-6 dOAOeY\">영상</a>","retrieved":1739264968952},{"title":"[인터뷰] '중증외상센터' 원작자 \"'히어로' 백강혁 보다 시스템을 바꿔야 한다\"","contents":"넷플릭스 시리즈 '중증외상센터' 원작자\n\"감독·배우, 원작 초월하는 작품 만들어\"\n\"의학 소재로 무협과 판타지  쓰고 싶다\"","link":"https://www.maxmovie.com/news/441502","retrieved":1739264969093,"image":"https://d3ihz389yobwks.cloudfront.net/1739233381096sw93O.jpg"},{"title":"고 김수미의 유작 '귀신경찰', 이제 안방에서 본다","contents":"설 연휴에 개봉, 11일  IPTV 및 VOD 공개\n아들로 만난 신현준과 따뜻한 코미디 그려","link":"https://www.maxmovie.com/news/441512","retrieved":1739261532843,"image":"https://d3ihz389yobwks.cloudfront.net/17392594509016mcTa.jpg"},{"title":"박형식의 처절한 복수극 '보물섬', 야망의 도전 통할까?","contents":"21일 첫 방송 SBS 금토드라마 \n허준호와 팽팽한 대립 관계로  \n마동석과 만난 '트웰브'도 공개","link":"https://www.maxmovie.com/news/441503","retrieved":1739264969100,"image":"https://d3ihz389yobwks.cloudfront.net/1739243714683Q9L2Y.png"},{"title":"민규동·이혜영·김성철, '파과'와 함께 베를린 간다","contents":"베를리날레 스페셜 초청\n60대 여성 킬러 이야기","link":"https://www.maxmovie.com/news/441507","retrieved":1739257756025,"image":"https://d3ihz389yobwks.cloudfront.net/1739244093752NOL44.jpg"},{"title":"극장에서 꼭 봐야 할 도경수의 슬픈 눈동자...'말없비' 입소문","contents":"2030세대 관객 집중적인 선택\n멜로 영화로 깊은 공감대 형성","link":"https://www.maxmovie.com/news/441504","retrieved":1739257756024,"image":"https://d3ihz389yobwks.cloudfront.net/17392359588644JCwM.jpg"},{"title":"'대세' 안야 테일러 조이·마일스 텔러의 '더 캐니언' 어떤 이야기?","contents":"최정예 저격수들의 비밀 작전 \n'닥터 스트레인지' 감독 연출","link":"https://www.maxmovie.com/news/441501","retrieved":1739264969108,"image":"https://d3ihz389yobwks.cloudfront.net/1739236001746OJG5L.jpg"},{"title":"[리뷰: 포테이토 지수 83%] '9월 5일: 위험한 특종' 저널리즘의 무게와 가치","contents":"1972년 '뮌헨 올림픽 참사' 소재 \n생중계로 테러 알린 방송사 모습  \n폐쇄성 강조하며 당시 현장 재현","link":"https://www.maxmovie.com/news/441495","retrieved":1739264969110,"image":"https://d3ihz389yobwks.cloudfront.net/1739177336989ut61R.jpg"},{"title":"[데일리 핫이슈] 피소 양익준 '고백' 예정대로 일정 소화·전지현 세무조사 관련 \"위법 행위 없었다\" 외","contents":"전날 일어난 엔터테인먼트 이슈를 소개합니다","link":"https://www.maxmovie.com/news/441500","retrieved":1739264969110,"image":"https://d3ihz389yobwks.cloudfront.net/1739191722855cb3c2.jpg"},{"title":"골든글로브·에미상 휩쓴 '쇼군' 시즌2 계획 첫 공개 \"가을 촬영 목표\"","contents":"사나다 히로유키가 밝힌 제작 일정\n크리틱스초이스에서도 4관왕 차지","link":"https://www.maxmovie.com/news/441498","retrieved":1739264969110,"image":"https://d3ihz389yobwks.cloudfront.net/1739173897061XkbAR.jpg"},{"title":"이정재·임지연 VS 박서준·원지안, 연예계 배경 드라마로 맞대결","contents":"로코 '얄미운 사랑' '경도를 기다리며'\n연예부 기자 주인공인 드라마 공통점","link":"https://www.maxmovie.com/news/441497","retrieved":1739264969111,"image":"https://d3ihz389yobwks.cloudfront.net/1739173133639p02Ym.jpg"},{"title":"\"뉴진스는 뉴진스\" 멤버들의 독자활동에 어도어 '반격' 시작","contents":"멤버들 새로운 그룹 이름 NJZ로 활동 \n어도어 \"전속계약은 유효\" 강경 입장","link":"https://www.maxmovie.com/news/441496","retrieved":1739264969113,"image":"https://d3ihz389yobwks.cloudfront.net/1739169658397dMoPl.png"},{"title":"'뉴토피아' 강점 VS 약점, 신선함 통했지만 지수 연기력 '호불호'","contents":"좀비물과 로맨틱 코미디의 결합 호평\n주연 지수의 발음·발성 등 지적 받아","link":"https://www.maxmovie.com/news/441492","retrieved":1739264969115,"image":"https://d3ihz389yobwks.cloudfront.net/173915217088973vOI.png"},{"title":"케이트·루니 마라 자매의 첫 동반 출연, '버킹 패스타드' 어떤 영화?","contents":"스토킹 벌인  채플린 자매 실화 다뤄\n베르너 헤어조크 감독 영화 복귀작","link":"https://www.maxmovie.com/news/441490","retrieved":1739264969116,"image":"https://d3ihz389yobwks.cloudfront.net/1739156107894mrd6Y.jpg"},{"title":"3시간35분에 인터미션까지...'브루탈리스트'의 고집은 통할까","contents":"긴 러닝타임에 포함된 '인터미션 15분'\nOTT콘텐츠가 가져온 관람 형태 변화?","link":"https://www.maxmovie.com/news/441493","retrieved":1739264969117,"image":"https://d3ihz389yobwks.cloudfront.net/17391565271423P1Gv.jpg"},{"title":"권상우 '히트맨2'·송혜교 '검은 수녀들',  나란히 손익분기점 돌파했지만...","contents":"총제작비 회수까진 관객 동원 필요\n입소문 힘입은 뒷심에 성패 갈릴 듯","link":"https://www.maxmovie.com/news/441487","retrieved":1739264969118,"image":"https://d3ihz389yobwks.cloudfront.net/1739149582755Afx6k.jpg"},{"title":"송혜교·공유, 노희경 작가와 그리는 \"야만과 폭력의 시기\"","contents":"넷플릭스 시리즈 '천천히 강렬하게'\n1960~80년대 한국 연예계가 배경","link":"https://www.maxmovie.com/news/441489","retrieved":1739264969120,"image":"https://d3ihz389yobwks.cloudfront.net/1739150889541EjjpA.png"},{"title":"봉준호 감독 \"비상계엄 사태, SF 영화보다 초현실적\"","contents":"\"어이가 없고 충격적인 일\"\n\"해외의 배우들이 연락와\"\n28일 영화 '미키 17' 개봉","link":"https://www.maxmovie.com/news/441491","retrieved":1739264969121,"image":"https://d3ihz389yobwks.cloudfront.net/17391504014277mgOF.png"}]}