{"title":"맥스무비","url":"https://www.maxmovie.com/","favicon":"https://www.maxmovie.com/favicon.ico","elements":[{"title":"내 여자친구의 모습이 생중계 되고 있다? 영화 '라방' 6월 개봉","contents":"박성웅 ·김희정·박선호 주연\n불법 라이브 방송 추적극","link":"https://www.maxmovie.com/news/433515","retrieved":1684141625263,"image":"https://d3ihz389yobwks.cloudfront.net/1684139048472jZ6lR.jpg"},{"title":"팬데믹의 결과? 3년간 프랜차이즈 영화 선호도 급상승","contents":"지난 3년간  박스오피스 1~7위까지 장악\n검증된 세계관·캐릭터 선호\n'분노의 질주10' '범죄도시3' 계속","link":"https://www.maxmovie.com/news/433511","retrieved":1684213504890,"image":"https://d3ihz389yobwks.cloudfront.net/1684134103806S8gkO.jpg"},{"title":"이효리가 시작했다! 김동률의 '황금가면 챌린지'","contents":"'유행의 아이콘' 이효리가 '황금가면 챌린지'를 시작했다. 이효리와 이상순 부부와 각별한 사이인 뮤지션 김동률의 신곡 '황금가면'을 응원하기 위한&nbsp;댄스 챌린지다.'황금가면 챌린지' 댄스를 선보이는 이효리 이상순 부부 (사진출처=이효리 SNS)이효리는 15일 SNS에 \"김동률의 황금가면\"이라는 설명과 함께 남편인 뮤지션 이상순과 함께 촬영한 영상을 게재해 눈","link":"https://www.maxmovie.com/news/433516","retrieved":1684145195740,"image":"https://d3ihz389yobwks.cloudfront.net/1684141227959jbRgU.png"},{"title":"[리뷰] 흥미로운 세계관, BUT 개연성 못 챙긴 '택배기사'","contents":"한국형 디스토피아  세계관 \n빈약한 개연성, 평면적 캐릭터","link":"https://www.maxmovie.com/news/433510","retrieved":1684197055766,"image":"https://d3ihz389yobwks.cloudfront.net/1684130910727TcmTU.jpg"},{"title":"이지훈·한승연,  '빈틈없는 사이'로 만난다","contents":"<span class=\"imgBox  floatLeft\"><a href=\"/news/433514\"><span class=\"imgBox\" style=\"background-image:url(https://d3ihz389yobwks.cloudfront.net/1684137226631mIAAq.jpg);background-size:cover\"></span></a></span><span class=\"textBox floatLeft stickerKey1\"><a href=\"/news/433514\"><h4>이지훈·한승연,  '빈틈없는 사이'로 만난다</h4></a><span>21시간 전<!-- --> · <a href=\"/writer/137\">박미애 기자</a></span></span>","link":"https://www.maxmovie.com/news/433514","retrieved":1684213504884,"image":"https://d3ihz389yobwks.cloudfront.net/1684137226631mIAAq.jpg"},{"title":"한석규 VS 이경영의 본격 대립… 최고 시청률 13.1% 기록","contents":"SBS 금토드라마 '낭만닥터 김사부3'의 한석규와 이경영이&nbsp;의사로서의 신념이 충돌하는 이야기를 통해 자체 최고시청률 13.1%를 기록했다.지난 13일 방송된 '낭만닥터 김사부3'(극본 강은경·연출 유인식) 6회에서는 수술 중 사망 확률이 높은 중증외상 환자를 두고 김사부(한석규)와 차진만(이경영)이 대립하는 모습이 그려졌다. 이날 방송의 시청률은&nbsp;전국 기준","link":"https://www.maxmovie.com/news/433512","retrieved":1684213504894,"image":"https://d3ihz389yobwks.cloudfront.net/1684133475366LafEW.jpg"},{"title":"한국영화아카데미, 연기 전공 신설 15일부터 모집","contents":"\"KAFA에게 배우게 된다\"\n\"KAFA에서 배우가 된다\"","link":"https://www.maxmovie.com/news/433509","retrieved":1684204407795,"image":"https://d3ihz389yobwks.cloudfront.net/1684113849139aMDEN.jpg"},{"title":"'우영우' 문지원 작가, 코다 소재 '데프 보이스'로 영화감독 데뷔","contents":"영화 '증인'과 드라마 '이상한 변호사 우영우'의 문지원 작가가 장편영화 감독으로 데뷔한다.'이상한 변호사 우영우' 스틸(사진제공=ENA)바른손스튜디오는 15일 \"문지원 작가의 감독 데뷔작 '데프 보이스'를 제작한다\"고 밝혔다.문지원 작가는 자폐 스펙트럼을 가진 여성을 주인공으로 내세워 사회적인 반향을 불러일으켰던 영화 '증인'과 드라마 '이상한 변호사 우","link":"https://www.maxmovie.com/news/433508","retrieved":1684204407795,"image":"https://d3ihz389yobwks.cloudfront.net/1684113450963KEn3R.jpg"},{"title":"뉴진스 다니엘, '인어공주' 한국어 더빙 주인공","contents":"그룹 활동 외 솔로 첫 도전 \n목소리 연기와 OST도 소화","link":"https://www.maxmovie.com/news/433507","retrieved":1684204407795,"image":"https://d3ihz389yobwks.cloudfront.net/1684049097464jNbCi.jpg"},{"title":"'슈퍼 마리오 브라더스' 200만 돌파","contents":"<span class=\"imgBox  floatLeft\"><a href=\"/news/433506\"><span class=\"imgBox\" style=\"background-image:url(https://d3ihz389yobwks.cloudfront.net/1684046122689yxoLB.jpg);background-size:cover\"></span></a></span><span class=\"textBox floatLeft stickerKey1\"><a href=\"/news/433506\"><h4>'슈퍼 마리오 브라더스' 200만 돌파 </h4></a><span>05월 14일<!-- --> · <a href=\"/writer/136\">이해리 기자</a></span></span>","link":"https://www.maxmovie.com/news/433506","retrieved":1684204407796,"image":"https://d3ihz389yobwks.cloudfront.net/1684046122689yxoLB.jpg"}]}