{"title":"맥스무비","url":"https://www.maxmovie.com/","favicon":"https://www.maxmovie.com/favicon.ico","elements":[{"title":"'쫓는 자' 김선호 vs '쫓기는 자' 강태주","contents":"'귀공자' 6월21일 개봉\n김선호 강태주 김강우 고아라 출연","link":"https://www.maxmovie.com/news/433519","retrieved":1684217427292,"image":"https://d3ihz389yobwks.cloudfront.net/1684217234140w0KwT.jpg"},{"title":"팬데믹의 결과? 3년간 프랜차이즈 영화 선호도 급상승","contents":"지난 3년간  박스오피스 1~7위까지 장악\n검증된 세계관·캐릭터 선호\n'분노의 질주10' '범죄도시3' 계속","link":"https://www.maxmovie.com/news/433511","retrieved":1684213504890,"image":"https://d3ihz389yobwks.cloudfront.net/1684134103806S8gkO.jpg"},{"title":"이지훈·한승연,  '빈틈없는 사이'로 만난다","contents":"이지훈과 한승연의 빈틈없는 동거가 시작된다.배급사 갤리온엔터테인먼트는 15일 \"이지훈 한승연 주연의 영화 '빈틈없는 사이'가 7월 개봉을 확정했다\"고 밝혔다.'빈틈없는 사이'는 방음이 안 되는 벽을 사이에 두고 서로의 일상을 공규하게 된 뮤지션 지망생 승진과 피규어 디자이너 라니의 이야기를 그린 로맨스 영화다.이지훈과 카라 한승연이 주연을 맡았다. 드라마","link":"https://www.maxmovie.com/news/433514","retrieved":1684213504884,"image":"https://d3ihz389yobwks.cloudfront.net/1684137226631mIAAq.jpg"},{"title":"내 여자친구의 모습이 생중계 되고 있다? 영화 '라방' 6월 개봉","contents":"박성웅 ·김희정·박선호 주연\n불법 라이브 방송 추적극","link":"https://www.maxmovie.com/news/433515","retrieved":1684141625263,"image":"https://d3ihz389yobwks.cloudfront.net/1684139048472jZ6lR.jpg"},{"title":"이선균·주지훈의 '탈출' 공개 전부터 140개국 선판매!","contents":"<span class=\"imgBox  floatLeft\"><a href=\"/news/433523\"><span class=\"imgBox\" style=\"background-image:url(https://d3ihz389yobwks.cloudfront.net/1684283054495mPwrw.jpg);background-size:cover\"></span></a></span><span class=\"textBox floatLeft stickerKey1\"><a href=\"/news/433523\"><h4>이선균·주지훈의 '탈출' 공개 전부터 140개국 선판매!</h4></a><span>4분 전<!-- --> · <a href=\"/writer/136\">이해리 기자</a></span></span>","link":"https://www.maxmovie.com/news/433523","retrieved":1684283659653,"image":"https://d3ihz389yobwks.cloudfront.net/1684283054495mPwrw.jpg"},{"title":"유아인 21시간 밤샘 조사, 구속영장 신청 여부 임박","contents":"마약 투약 혐의를 받는&nbsp;배우 유아인이 약 21시간에 걸친 밤샘 조사를 받았다. 경찰은 조만간 조사를 마무리하고 구속영장 신청 여부를 결정할 계획이다유아인 (사진제공=넷플릭스)프로포폴과 대마 등 5종의 마약류 투약 혐의를 받는 유아인이 16일 오전 9시 서울경찰청 마약범죄수사대에 출석해 17일 오전 6시30분까지 약 21시간동안 조사를 받았다. 마약류관리법","link":"https://www.maxmovie.com/news/433522","retrieved":1684283659662,"image":"https://d3ihz389yobwks.cloudfront.net/1684282510300RKtBR.jpg"},{"title":"[오늘 뭘 볼까] 전편보다 더 큰 스케일로 돌아온 영화 '유랑지구2'","contents":"오늘, 볼만한 작품을 추천합니다.◆ '유랑지구2''유랑지구2' 스틸(사진제공=BoXoo엔터테인먼트)태양계 소멸의 위기를 맞은 인류는 지구 표면에 거대한 엔진을 달아 궤도를 옮기는 유랑지구 프로젝트에 돌입한다. 하지만 데이터베이스로 영생을 가지려는 디지털 라이프와 대립하게 되며 프로젝트는 난관에 부딪히고, 그 과정 속 달과의 충돌이라는 예상치 못한 대재앙에","link":"https://www.maxmovie.com/news/433521","retrieved":1684283659662,"image":"https://d3ihz389yobwks.cloudfront.net/1684226183673rfF7y.jpg"},{"title":"어제의 동지가 오늘은 적? 1위 지각변동 예고","contents":"어제의 동지가 오늘의 적이 됐다.국내 박스오피스 1위 '가디언즈 오브 갤럭시3'('가오갤3')과 그에 도전장을 내미는 '분노의 질주:라이드 오어 다이'('분노의 질주10')가 그것.(사진=영화 '분노의 질주:라이드 오어 다이' 스틸)'가오갤3'과 '분노의 질주10'의 승부에 관심이 쏠리는 건, 할리우드 대표 프랜차이즈 영화의 승부기도 하지만 빈 디젤이 두","link":"https://www.maxmovie.com/news/433518","retrieved":1684231611916,"image":"https://d3ihz389yobwks.cloudfront.net/1684201138798gjtgs.jpg"},{"title":"이효리가 시작했다! 김동률의 '황금가면 챌린지'","contents":"'유행의 아이콘' 이효리가 '황금가면 챌린지'를 시작했다. 이효리와 이상순 부부와 각별한 사이인 뮤지션 김동률의 신곡 '황금가면'을 응원하기 위한&nbsp;댄스 챌린지다.'황금가면 챌린지' 댄스를 선보이는 이효리 이상순 부부 (사진출처=이효리 SNS)이효리는 15일 SNS에 \"김동률의 황금가면\"이라는 설명과 함께 남편인 뮤지션 이상순과 함께 촬영한 영상을 게재해 눈","link":"https://www.maxmovie.com/news/433516","retrieved":1684145195740,"image":"https://d3ihz389yobwks.cloudfront.net/1684141227959jbRgU.png"},{"title":"한석규 VS 이경영의 본격 대립… 최고 시청률 13.1% 기록","contents":"<span class=\"imgBox  floatLeft\"><a href=\"/news/433512\"><span class=\"imgBox\" style=\"background-image:url(https://d3ihz389yobwks.cloudfront.net/1684133475366LafEW.jpg);background-size:cover\"></span></a></span><span class=\"textBox floatLeft stickerKey1\"><a href=\"/news/433512\"><h4>한석규 VS 이경영의 본격 대립… 최고 시청률 13.1% 기록</h4></a><span>05월 15일<!-- --> · <a href=\"/writer/124\">김희주 기자</a></span></span>","link":"https://www.maxmovie.com/news/433512","retrieved":1684213504894,"image":"https://d3ihz389yobwks.cloudfront.net/1684133475366LafEW.jpg"}]}