{"title":"맥스무비","url":"https://www.maxmovie.com/","favicon":"https://www.maxmovie.com/favicon.ico","elements":[{"title":"손예진이 공개한 행복한 근황 \"현빈보다 나를 더 닮은 아들\"","contents":"유튜브 채널 출연해 근황 공개\n결혼&amp;출산 이후 육아에 집중","link":"https://www.maxmovie.com/news/434911","retrieved":1695891971799,"image":"https://d3ihz389yobwks.cloudfront.net/1695890527882owmtk.jpg"},{"title":"고윤정 이어...신시아→정준원, '슬의생' 스핀오프 라인업 살펴보니","contents":"고윤정 이어 신시아, 한예지, 강유석, 정준원 합류\n'슬의생' 스핀오프로 내년 상반기 방송","link":"https://www.maxmovie.com/news/434902","retrieved":1695865258201,"image":"https://d3ihz389yobwks.cloudfront.net/1695864205460MOSpr.jpg"},{"title":"'천박사' 강동원, \"나를 노출시키지 않으려고 해\" 왜?","contents":"'천박사' 홍보 위해 '피식쇼' 출연한 강동원\n\"100평 부지 단독주택에 산다\" 공개해","link":"https://www.maxmovie.com/news/434909","retrieved":1695895591306,"image":"https://d3ihz389yobwks.cloudfront.net/1695881084461OczOJ.png"},{"title":"강동원·송중기·김남길·안효섭, '맥스무비' 독자에게 보낸 추석인사!","contents":"송강호·류승룡 등 배우들의 연휴 인사\n추석 영화 및 시리즈 장식한 주인공들","link":"https://www.maxmovie.com/news/434895","retrieved":1695895591306,"image":"https://d3ihz389yobwks.cloudfront.net/1695777770569lHj7r.jpg"},{"title":"이서진, 윤여정 이어 후크엔터 떠난다...\"9월 말 계약 종료\"","contents":"<span class=\"imgBox  floatLeft\"><a href=\"/news/434908\"><span class=\"imgBox\" style=\"background-image:url(https://d3ihz389yobwks.cloudfront.net/1695880437414zGYay.jpg);background-size:cover\"></span></a></span><span class=\"textBox floatLeft stickerKey1\"><a href=\"/news/434908\"><h4>이서진, 윤여정 이어 후크엔터 떠난다...\"9월 말 계약 종료\"</h4></a><span>23시간 전<!-- --> · <a href=\"/writer/142\">조현주 기자</a></span></span>","link":"https://www.maxmovie.com/news/434908","retrieved":1695938660343,"image":"https://d3ihz389yobwks.cloudfront.net/1695880437414zGYay.jpg"},{"title":"이동욱·임수정이 그리는 '싱글 인 서울', 11월29일 관객 찾는다","contents":"현실 공감 로맨스 표방\n이동욱, 임수정이 그릴 싱글 라이프는?","link":"https://www.maxmovie.com/news/434907","retrieved":1695881374146,"image":"https://d3ihz389yobwks.cloudfront.net/1695878717106ilrO6.png"},{"title":"뉴진스, 추석 맞아 한복 화보 공개...\"풍요롭고 따뜻한 한가위 보내길\"","contents":"고운 한복 자태 과시\n추석 연휴 계획도 공유","link":"https://www.maxmovie.com/news/434906","retrieved":1695960499809,"image":"https://d3ihz389yobwks.cloudfront.net/1695954253314EXqcj.png"},{"title":"'알쓸인잡' 인연...방탄소년단 RM, 대한법의학회에 1억원 기부","contents":"'알쓸인잡' 이호 교수와의 인연\n\"법의학회 발전에 보탬 되길\"","link":"https://www.maxmovie.com/news/434905","retrieved":1695874065030,"image":"https://d3ihz389yobwks.cloudfront.net/1695872741809LvVMs.jpg"},{"title":"'용감한 형사들3' 바다에 빠진 실종자는 어디에...사채 빚 갚으려는 거짓실종?","contents":"실종사건의 전말은?\n오는 29일 방송","link":"https://www.maxmovie.com/news/434904","retrieved":1695870448226,"image":"https://d3ihz389yobwks.cloudfront.net/1695869272417uZZeR.jpg"},{"title":"전편 능가하는 공포? '더 넌2', 박스오피스 3위로 등판","contents":"<span class=\"imgBox  floatLeft\"><a href=\"/news/434903\"><span class=\"imgBox\" style=\"background-image:url(https://d3ihz389yobwks.cloudfront.net/1695866932981BVErV.jpg);background-size:cover\"></span></a></span><span class=\"textBox floatLeft stickerKey1\"><a href=\"/news/434903\"><h4>전편 능가하는 공포? '더 넌2', 박스오피스 3위로 등판</h4></a><span>09월 28일<!-- --> · <a href=\"/writer/142\">조현주 기자</a></span></span>","link":"https://www.maxmovie.com/news/434903","retrieved":1695938660381,"image":"https://d3ihz389yobwks.cloudfront.net/1695866932981BVErV.jpg"}]}