{"title":"맥스무비","url":"https://www.maxmovie.com/","favicon":"https://www.maxmovie.com/favicon.ico","elements":[{"contents":"<a href=\"/movies\" style=\"color:#222\" class=\"EachMenu__NavHref-sc-9yn4xi-6 dOAOeY\">영화</a>","retrieved":1720080639201},{"contents":"<a href=\"/peoples\" style=\"color:#222\" class=\"EachMenu__NavHref-sc-9yn4xi-6 dOAOeY\">피플</a>","retrieved":1720080639202},{"contents":"<a href=\"/series\" style=\"color:#222\" class=\"EachMenu__NavHref-sc-9yn4xi-6 dOAOeY\">시리즈</a>","retrieved":1720080639207},{"contents":"<a href=\"/moviereview\" style=\"color:#222\" class=\"EachMenu__NavHref-sc-9yn4xi-6 dOAOeY\">영화 리뷰</a>","retrieved":1720080639207},{"contents":"<a href=\"/seriesreview\" style=\"color:#222\" class=\"EachMenu__NavHref-sc-9yn4xi-6 dOAOeY\">시리즈 리뷰</a>","retrieved":1720080639210},{"contents":"<a href=\"/event\" style=\"color:#222\" class=\"EachMenu__NavHref-sc-9yn4xi-6 dOAOeY\">시사회·이벤트</a>","retrieved":1720080639214},{"contents":"<a href=\"/eventResult\" style=\"color:#222\" class=\"EachMenu__NavHref-sc-9yn4xi-6 dOAOeY\">당첨자 발표</a>","retrieved":1720080639220},{"contents":"<a href=\"/photo\" style=\"color:#222\" class=\"EachMenu__NavHref-sc-9yn4xi-6 dOAOeY\">포토</a>","retrieved":1720080639225},{"contents":"<a href=\"/youtube\" style=\"color:#222\" class=\"EachMenu__NavHref-sc-9yn4xi-6 dOAOeY\">영상</a>","retrieved":1720080639226},{"title":"여름 극장가 뜻밖의 출격...이준호·블랙핑크·박은빈·임영웅까지","contents":"7~8월 스타들의 공연 실황 영화 개봉\n막강 팬덤의 집결→ 관객 동원 기대감","link":"https://www.maxmovie.com/news/438496","retrieved":1720066142434,"image":"https://d3ihz389yobwks.cloudfront.net/1720057186739bSgoB.jpg"},{"title":"'헤드윅' 넘어 '파일럿'까지...조정석의 여장, '흥행 치트키' 될까","contents":"7월31일 개봉, 김한결 감독 연출작\n재취업 위해 여장 불사 파일럿 이야기","link":"https://www.maxmovie.com/news/438491","retrieved":1720073506070,"image":"https://d3ihz389yobwks.cloudfront.net/1720054316786EPeS4.jpg"},{"title":"이제훈·구교환 해냈다…韓영화 '탈주' 22일만에 정상","contents":"'탈주', '인사이드 아웃2' 제치고 1위 출발\n근소한 차이로 치열한 정상 다툼 예상","link":"https://www.maxmovie.com/news/438490","retrieved":1720073506073,"image":"https://d3ihz389yobwks.cloudfront.net/1720048045938yDSqI.jpg"},{"title":"'극장판 귀멸의 칼날: 무한성 편'에 높아지는 관심…언제쯤 공개?","contents":"최종장 극장판 3부작으로 공개\n이르면 내년 여름…현지 언론 전망","link":"https://www.maxmovie.com/news/438503","retrieved":1720080639356,"image":"https://d3ihz389yobwks.cloudfront.net/17200775537533iMSO.jpg"},{"title":"[#Shorts] 하트 거부? 라이언 레이놀즈·휴 잭맨, 절친인가 상극인가","contents":"내한 첫날 고척스카이돔에서 야구 관람\n7월24일 개봉하는 '데드풀과 울버린'","link":"https://www.maxmovie.com/news/438500","retrieved":1720080639356,"image":"https://i.ytimg.com/vi/-gduEKFvogo/0.jpg"},{"title":"대한·민국·만세 '삼둥이 효과'...'유퀴즈' 역대 최고 시청률 달성","contents":"랜선 이모, 삼촌들 총집결 관심 집중\n170cm 훌쩍 넘는 초등 6학년 성장","link":"https://www.maxmovie.com/news/438494","retrieved":1720076935937,"image":"https://d3ihz389yobwks.cloudfront.net/1720058525145CGEzS.jpg"},{"title":"[오늘 뭘 볼까] 보통의 하루가 선사하는 찬란함, 영화 '퍼펙트 데이즈'","contents":"일본 배우 야쿠쇼 코지 주연\n아날로그 감성 가득한 도쿄 배경","link":"https://www.maxmovie.com/news/438484","retrieved":1720066142434,"image":"https://d3ihz389yobwks.cloudfront.net/1719981777003KaPK0.jpg"},{"title":"[데일리 핫이슈] 변우석·김혜윤 '사귀지?' 효과, '9월 출산' 이유영 의상 회제 외","contents":"전날 일어난 엔터테인먼트 이슈를 소개합니다","link":"https://www.maxmovie.com/news/438483","retrieved":1720076935937,"image":"https://d3ihz389yobwks.cloudfront.net/1719990034597E6JlI.png"},{"title":"'오징어 게임2' 글로벌 빅시즌 공략, 크리스마스 공개 전망","contents":"주연 배우 공유 \"크리스마스 공개\" 밝혀\n넷플릭스 공식 발표 아직...최대 기대작","link":"https://www.maxmovie.com/news/438486","retrieved":1720080639361,"image":"https://d3ihz389yobwks.cloudfront.net/1719991233763v5wqg.jpg"},{"title":"용산에서 나고 자란 'YS 블락', 정규 2집 '용산' 발매","contents":"3곡의 타이틀곡 포함 총 12곡 수록 \n용산에서 겪은 다양한 일화 모티프","link":"https://www.maxmovie.com/news/438485","retrieved":1719997700508,"image":"https://d3ihz389yobwks.cloudfront.net/1719988703686PQpkt.jpg"},{"title":"'범죄도시' 1000만 흥행 감독들, 처음으로 동반 무대 오른다","contents":"6일 'BIFAN 스트리트: 팬터뷰' 참여 \n2·3편 이상용 감독, 4편 허명행 감독","link":"https://www.maxmovie.com/news/438478","retrieved":1720076935943,"image":"https://d3ihz389yobwks.cloudfront.net/1719968347508vTbP4.jpg"},{"title":"'탈주' 등판…디즈니에 위협될까, 韓영화 간 경쟁될까","contents":"7월 시작되자 가열되는 여름 극장 대전\n'탈주'·'인사이드 아웃2'·'핸섬가이즈' 3파전","link":"https://www.maxmovie.com/news/438481","retrieved":1720076935951,"image":"https://d3ihz389yobwks.cloudfront.net/1719972755157A3eiH.jpg"},{"title":"임영웅 주연 단편영화, 쿠팡플레이·티빙 6일 동시 공개... 왜?","contents":"부담 없이 감상할 수 있는 방법 모색\n황폐한 세상을 살아가는 인물 소화","link":"https://www.maxmovie.com/news/438475","retrieved":1720080639373,"image":"https://d3ihz389yobwks.cloudfront.net/1719965568057bJ2do.jpg"},{"title":"'가여운 것들'도 제쳤다, '존 오브 인터레스트'는 어떻게 흥행했나","contents":"\"보여주지 않으면서 보여주는 영화\" 호평\n\"취향 드러낼 수 있는 독립영화 팬층 유입\"","link":"https://www.maxmovie.com/news/438473","retrieved":1720076935952,"image":"https://d3ihz389yobwks.cloudfront.net/1719910664278ZGzyr.jpg"},{"title":"배우 이유영, 결혼·임신 동시 발표 \"9월 출산\"","contents":"5월 혼인신고·9월 출산 예정 '겹경사'\n\"출산일 임박 별도의 결혼식은 미정\"","link":"https://www.maxmovie.com/news/438474","retrieved":1720076935954,"image":"https://d3ihz389yobwks.cloudfront.net/1719964154475RjHWG.jpg"},{"title":"[데일리 핫이슈] 김수현·김지원 '럽스타그램' 의혹, '자숙' 김새론 카페 취업 외","contents":"전날 일어난 엔터테인먼트 이슈를 소개합니다","link":"https://www.maxmovie.com/news/438467","retrieved":1720076935954,"image":"https://d3ihz389yobwks.cloudfront.net/17198928469222gZtJ.jpg"},{"title":"[오늘 뭘 볼까] 이제훈 쫓는 구교환, 그 이유는… 영화 '탈주'","contents":"홍사빈과 송강·이솜·신현지 등  출연\n북한병사 쫓는 보위부 장교의 이야기","link":"https://www.maxmovie.com/news/438471","retrieved":1720069796335,"image":"https://d3ihz389yobwks.cloudfront.net/17199003430241yumS.jpg"}]}