{"title":"맥스무비","url":"https://www.maxmovie.com/","favicon":"https://www.maxmovie.com/favicon.ico","elements":[{"contents":"<a href=\"/movies\" style=\"color:#222\" class=\"EachMenu__NavHref-sc-9yn4xi-6 dOAOeY\">영화</a>","retrieved":1741308201423},{"contents":"<a href=\"/peoples\" style=\"color:#222\" class=\"EachMenu__NavHref-sc-9yn4xi-6 dOAOeY\">피플</a>","retrieved":1741308201424},{"contents":"<a href=\"/series\" style=\"color:#222\" class=\"EachMenu__NavHref-sc-9yn4xi-6 dOAOeY\">시리즈</a>","retrieved":1741308201425},{"contents":"<a href=\"/moviereview\" style=\"color:#222\" class=\"EachMenu__NavHref-sc-9yn4xi-6 dOAOeY\">영화 리뷰</a>","retrieved":1741308201426},{"contents":"<a href=\"/seriesreview\" style=\"color:#222\" class=\"EachMenu__NavHref-sc-9yn4xi-6 dOAOeY\">시리즈 리뷰</a>","retrieved":1741308201427},{"contents":"<a href=\"/event\" style=\"color:#222\" class=\"EachMenu__NavHref-sc-9yn4xi-6 dOAOeY\">시사회·이벤트</a>","retrieved":1741308201428},{"contents":"<a href=\"/eventResult\" style=\"color:#222\" class=\"EachMenu__NavHref-sc-9yn4xi-6 dOAOeY\">당첨자 발표</a>","retrieved":1741308201429},{"contents":"<a href=\"/photo\" style=\"color:#222\" class=\"EachMenu__NavHref-sc-9yn4xi-6 dOAOeY\">포토</a>","retrieved":1741308201430},{"contents":"<a href=\"/youtube\" style=\"color:#222\" class=\"EachMenu__NavHref-sc-9yn4xi-6 dOAOeY\">영상</a>","retrieved":1741308201432},{"title":"[데일리 핫이슈] 수지 '백설공주' OST 컬래버레이션, 하정우 'SNL 코리아' 호스트 외","contents":"전날 일어난 엔터테인먼트 이슈를 소개합니다","link":"https://www.maxmovie.com/news/441807","retrieved":1741308201580,"image":"https://d3ihz389yobwks.cloudfront.net/1741249720553AtgaH.jpg"},{"title":"2년 만에 돌아온 일본 스릴러 '간니발' 시즌2 관전 포인트","contents":"19일 디즈니+ 공개 야기라 유야 주연 \n가타야마 신조 감독의 날카로운 시선","link":"https://www.maxmovie.com/news/441802","retrieved":1741241645600,"image":"https://d3ihz389yobwks.cloudfront.net/1741231964033H65YU.jpg"},{"title":"[오늘 뭘 볼까] 봄을 닮은 청량한 로맨스 영화 '장난을 잘 치는 타카기 양'","contents":"동명만화 원작, 드라마도 제작 \n10년 만에 재회한 청춘의 사랑","link":"https://www.maxmovie.com/news/441806","retrieved":1741298910987,"image":"https://d3ihz389yobwks.cloudfront.net/1741231227602nAR6j.jpg"},{"title":"봉준호 감독 '미키 17' 북미 첫 주 수입 전망...약 290억원","contents":"북미에서 7일 개봉 오프닝 성적 관심 \n감독의 독창적인 세계 주목 긍정 전망","link":"https://www.maxmovie.com/news/441812","retrieved":1741308201582,"image":"https://d3ihz389yobwks.cloudfront.net/1741245587913q0bA8.jpg"},{"title":"'토르' 크리스 햄스워스, 신촌에 뜬 이유 밝혀졌다","contents":"다큐멘터리 '리미트리스2' 촬영 위해 \n김동현과 스파링 등 '액션 본능' 눈길","link":"https://www.maxmovie.com/news/441803","retrieved":1741248747645,"image":"https://d3ihz389yobwks.cloudfront.net/17412294008186c9ho.jpg"},{"title":"장동건·탕웨이, 아시아필름어워즈 '아시아영화액설런스상' 수상","contents":"아시아영화 발전과 문화 확대 공로 인정\n장동건 \"매우 영광이고 진심으로 감사\"\n탕웨이 \"홍콩은 나에게 항상 특별한 곳\"","link":"https://www.maxmovie.com/news/441798","retrieved":1741302554292,"image":"https://d3ihz389yobwks.cloudfront.net/1741225186741CW97u.jpg"},{"title":"교황의 죽음과 비밀스러운 선거 '콘클라베', 박스오피스 2위 출발","contents":"5일 개봉 첫날 1만796명 관객 동원\n성스러운 의식을 스릴러로 풀어내","link":"https://www.maxmovie.com/news/441800","retrieved":1741302554293,"image":"https://d3ihz389yobwks.cloudfront.net/1741220921695hoAzx.jpg"},{"title":"배우 이영애는 왜 32년 만에 연극 무대를 택했나","contents":"5월7일부터 한달간 '헤다 가블러' 올라 \n최근 다양한 연기 도전과 변신의 일환 \n10월 방송하는 드라마 '은수 좋은 날'도","link":"https://www.maxmovie.com/news/441801","retrieved":1741302554297,"image":"https://d3ihz389yobwks.cloudfront.net/17412227207296Qddz.png"},{"title":"[오늘 뭘 볼까] 케이트 블란쳇과 잭 블랙의 은하계 모험 '보더랜드'","contents":"동명 게임을 실사 영화로 옮긴 작품\n명배우들이 참여한 오합지졸 모험담","link":"https://www.maxmovie.com/news/441789","retrieved":1741302554299,"image":"https://d3ihz389yobwks.cloudfront.net/17411532708756vlxj.jpg"},{"title":"[데일리 핫이슈] 시우민과 MC몽의 SM 저격, 윤하 결혼 발표 외","contents":"전날 일어난 엔터테인먼트 이슈를 소개합니다","link":"https://www.maxmovie.com/news/441788","retrieved":1741308201599,"image":"https://d3ihz389yobwks.cloudfront.net/1741159165601Ytrwv.jpg"},{"title":"[리뷰: 포테이토 지수 82%] '침범', 모성에 대한 묵직한 질문","contents":"가학적 성향의  딸이 무서운  엄마\n곽선영·권유리·이설·기소유 호연","link":"https://www.maxmovie.com/news/441797","retrieved":1741302554299,"image":"https://d3ihz389yobwks.cloudfront.net/1741177120645g6n6c.jpg"},{"title":"코미디, 액션, 로맨스 다 되네...서강준 매력 집합한 '언더커버 하이스쿨'","contents":"'언더커버 하이스쿨'로 3년 만의 복귀\n\"표정과 움직임에서 진정성 묻어 나와\"\n1회 시청률 5.6%로 출발해 4회 8.3%","link":"https://www.maxmovie.com/news/441790","retrieved":1741302554300,"image":"https://d3ihz389yobwks.cloudfront.net/1741156067440YAaiN.jpg"},{"title":"무속의 세계 추적하는 다큐영화 '당골', 3월 관객과 만난다","contents":"호러 오컬트 접목한 페이크 다큐 형식","link":"https://www.maxmovie.com/news/441791","retrieved":1741308201601,"image":"https://d3ihz389yobwks.cloudfront.net/1741156481031qv473.jpg"},{"title":"아이유·박보검·감독이 답했다. '폭싹 속았수다' 둘러싼 궁금증","contents":"\"따뜻한 귤차 같은 드라마이길 바란다\"\n\"600억원 제작비가 아깝지 않게 연출\"\n총 16부작, 4편씩 4주 동안 공개 예정","link":"https://www.maxmovie.com/news/441784","retrieved":1741302554304,"image":"https://d3ihz389yobwks.cloudfront.net/1741148218754uIjue.png"},{"title":"내년 상반기 돌아오는 '두 번째 시그널'에 담길 내용은","contents":"시간 초월해 미제 사건 해결하는 수사물\n드러난 사건의 배후, 시즌2서 응징할까","link":"https://www.maxmovie.com/news/441781","retrieved":1741302554305,"image":"https://d3ihz389yobwks.cloudfront.net/1741144487210J57p3.jpg"},{"title":"'너자2' 마침내 20억 달러 눈앞...전 세계 흥행 역사 새롭게 쓴다","contents":"전체 수익의 99% 중국 본토에서 거둬 \n단체→N차 관람 '기록 만들기'에 열중","link":"https://www.maxmovie.com/news/441778","retrieved":1741302554309,"image":"https://d3ihz389yobwks.cloudfront.net/1741124656879FMiDP.jpg"},{"title":"'괜괜괜'·'선의의 경쟁' 정수빈이 그린 낯선 얼굴의 소녀들","contents":"동시기 공개한 작품 속 '두 얼굴'의 10대 \n1998년생 신인, 드라마 '트롤리'로 주목","link":"https://www.maxmovie.com/news/441771","retrieved":1741302554310,"image":"https://d3ihz389yobwks.cloudfront.net/1741141433858Gcnzn.png"}]}