{"title":"맥스무비","url":"https://www.maxmovie.com/","favicon":"https://www.maxmovie.com/favicon.ico","elements":[{"title":"진구·공승연 '전주로 오세요'","contents":"제24회 전주국제영화제 개막식 사회\n10일간 247편 상영…개막작 '토리와 로키타'","link":"https://www.maxmovie.com/news/433325","retrieved":1681437335237,"image":"https://d3ihz389yobwks.cloudfront.net/1681433664757dR3JA.jpg"},{"title":"[단독] 韓 첫 미국 골든글로브 투표  설재원 \"韓영화 영향력 넓히기 일조\"","contents":"미국 골든글로브 한국인 최초 국제투표단 \n내년 1월7일 시상식 투표 참여","link":"https://www.maxmovie.com/news/433321","retrieved":1681380355666,"image":"https://d3ihz389yobwks.cloudfront.net/1681379071307yy7BO.jpg"},{"title":"블랙핑크 제니 칸 가나…'더 아이돌' 초청","contents":"HBO '더 아이돌' 칸 비경쟁 초청\n블랙핑크 제니 연기 도전…더 위켄드, 릴리 로즈 뎁 등 출연","link":"https://www.maxmovie.com/news/433326","retrieved":1681437335240,"image":"https://d3ihz389yobwks.cloudfront.net/16814356078320dkDs.jpg"},{"title":"송중기,  배우이자 제작자로 칸 첫 입성","contents":"출연하고 제작까지 맡은 영화 '화란' \n칸 국제영화제 주목할만한 시선 부문 초청","link":"https://www.maxmovie.com/news/433322","retrieved":1681437335241,"image":"https://d3ihz389yobwks.cloudfront.net/1681378902016cKxWr.jpg"},{"title":"로튼토마토 92%에 빛나는 스페인 스릴러 '피기'","contents":"<span class=\"imgBox  floatLeft\"><a href=\"/news/433318\"><span class=\"imgBox\" style=\"background-image:url(https://d3ihz389yobwks.cloudfront.net/168135434066194lbe.jpg);background-size:cover\"></span></a></span><span class=\"textBox floatLeft stickerKey1\"><a href=\"/news/433318\"><h4>로튼토마토 92%에 빛나는 스페인 스릴러 '피기' </h4></a><span>04월 13일<!-- --> · <a href=\"/writer/136\">이해리 기자</a></span></span>","link":"https://www.maxmovie.com/news/433318","retrieved":1681362334357,"image":"https://d3ihz389yobwks.cloudfront.net/168135434066194lbe.jpg"},{"title":"박해일 새둥지 틀다","contents":"박해일(사진제공=메이크스타)배우 박해일이 메이크스타에 새 둥지를 틀었다.13일 메이크스타는 \"박해일과 전속계약을 체결했다\"고 밝혔다.박해일은 연극 '청춘예찬'(2000)으로 연기를 시작해 영화 '살인의 추억' '국화꽃 향기'(2003) '연애의 목적'(2005) '괴물'(2006) '이끼'(2010) '덕혜옹주'(2016) 등에 출연했다. 지난해 제75회","link":"https://www.maxmovie.com/news/433317","retrieved":1681355232264,"image":"https://d3ihz389yobwks.cloudfront.net/1681352734979vq9Js.png"},{"title":"'존 윅4', 개봉 첫 날 '스즈메' 잡았다","contents":"개봉 첫 날 박스오피스 1위\n36일간 정상 지킨 '스즈메의 문단속' 2위로","link":"https://www.maxmovie.com/news/433313","retrieved":1681445284756,"image":"https://d3ihz389yobwks.cloudfront.net/1681346202691NXJPr.jpg"},{"title":"김희선의 '가스라이팅' 성공할까","contents":"드라마 '가스라이팅' 주연\n이혜영 김남희 강해림과 호흡","link":"https://www.maxmovie.com/news/433312","retrieved":1681445284760,"image":"https://d3ihz389yobwks.cloudfront.net/1681345224045ysQuE.jpg"},{"title":"[오늘 뭘 볼까] 스티븐 연이 보여주는 짜릿한 복수! ‘성난 사람들’","contents":"오늘, 볼만한 작품을 추천합니다.◆ 넷플릭스 오리지널 시리즈 ‘성난 사람들(비프)’넷플릭스 시리즈 '성난 사람들' (사진제공 = 넷플릭스)넷플릭스 시리즈 ‘성난 사람들’은 일이 잘 풀리지 않는 도급업자 대니와 삶이 만족스럽지 않은 사업가 에이미 사이에서 벌어진 난폭 운전 사건이 불러오는 여파를 담은 작품이다. 주차장에서 사고를 낼 뻔하고 욕설을 날린 채 내","link":"https://www.maxmovie.com/news/433310","retrieved":1681445284762,"image":"https://d3ihz389yobwks.cloudfront.net/1681277073951Cf0Wh.jpg"},{"title":"마약 투약 유아인, 확인되지 않은 뉴스에 '법적 대응'","contents":"<span class=\"imgBox  floatLeft\"><a href=\"/news/433309\"><span class=\"imgBox\" style=\"background-image:url(https://d3ihz389yobwks.cloudfront.net/1681266553756zHaez.jpg);background-size:cover\"></span></a></span><span class=\"textBox floatLeft stickerKey1\"><a href=\"/news/433309\"><h4>마약 투약 유아인, 확인되지 않은 뉴스에 '법적 대응'  </h4></a><span>04월 12일<!-- --> · <a href=\"/writer/136\">이해리 기자</a></span></span>","link":"https://www.maxmovie.com/news/433309","retrieved":1681445284749,"image":"https://d3ihz389yobwks.cloudfront.net/1681266553756zHaez.jpg"}]}