{"title":"맥스무비","url":"https://www.maxmovie.com/","favicon":"https://www.maxmovie.com/favicon.ico","elements":[{"contents":"<a href=\"/movies\" style=\"color:#222\" class=\"EachMenu__NavHref-sc-9yn4xi-6 dOAOeY\">영화</a>","retrieved":1711634710153},{"contents":"<a href=\"/peoples\" style=\"color:#222\" class=\"EachMenu__NavHref-sc-9yn4xi-6 dOAOeY\">피플</a>","retrieved":1711634710153},{"contents":"<a href=\"/series\" style=\"color:#222\" class=\"EachMenu__NavHref-sc-9yn4xi-6 dOAOeY\">시리즈</a>","retrieved":1711634710154},{"contents":"<a href=\"/moviereview\" style=\"color:#222\" class=\"EachMenu__NavHref-sc-9yn4xi-6 dOAOeY\">영화 리뷰</a>","retrieved":1711634710154},{"contents":"<a href=\"/seriesreview\" style=\"color:#222\" class=\"EachMenu__NavHref-sc-9yn4xi-6 dOAOeY\">시리즈 리뷰</a>","retrieved":1711634710156},{"contents":"<a href=\"/event\" style=\"color:#222\" class=\"EachMenu__NavHref-sc-9yn4xi-6 dOAOeY\">시사회·이벤트</a>","retrieved":1711634710160},{"contents":"<a href=\"/eventResult\" style=\"color:#222\" class=\"EachMenu__NavHref-sc-9yn4xi-6 dOAOeY\">당첨자 발표</a>","retrieved":1711634710160},{"contents":"<a href=\"/photo\" style=\"color:#222\" class=\"EachMenu__NavHref-sc-9yn4xi-6 dOAOeY\">포토</a>","retrieved":1711634710176},{"contents":"<a href=\"/youtube\" style=\"color:#222\" class=\"EachMenu__NavHref-sc-9yn4xi-6 dOAOeY\">영상</a>","retrieved":1711634710192},{"title":"BIFF, 올해는  2인 부집행위원장 제체로 '공석 메운다'","contents":"박도신·강승아 부집행위원장이 집행위원장 대행","link":"https://www.maxmovie.com/news/437210","retrieved":1711609541985,"image":"https://d3ihz389yobwks.cloudfront.net/1711603570734scKie.jpg"},{"title":"'에스파 영화' 개봉…40개국 글로벌 팬 만난다","contents":"걸그룹 에스파 월드 투어 공연 실황 영화\n한국과 일본 비롯 전 세계 40여 개국 개봉","link":"https://www.maxmovie.com/news/437209","retrieved":1711595253476,"image":"https://d3ihz389yobwks.cloudfront.net/17115933492624rphK.jpg"},{"title":"배우 아닌 가수 조정석은 어떨까? '아내' 거미의 든든한 지원사격","contents":"조정석, 거미·다듀 지원 가수 데뷔 쇼케이스\n넷플릭스 '신인가수 조정석', 데뷔 과정 공개","link":"https://www.maxmovie.com/news/437206","retrieved":1711616865379,"image":"https://d3ihz389yobwks.cloudfront.net/17115914182569fp9I.jpg"},{"title":"제천국제음악영화제, 9월로 개최일 변경","contents":"\"궂은 날씨 등 고려\" 8월→9월 개최 확정\n장·단편영화 및 '메이드 인 제천' 상영작 공모 중","link":"https://www.maxmovie.com/news/437218","retrieved":1711620469411,"image":"https://d3ihz389yobwks.cloudfront.net/1711619235355YTY07.jpg"},{"title":"윤여정·이민호 '파친코'부터 톰 행크스 '핀치'까지","contents":"'N차 정주행' 유발하는 애플TV+ 오리지널 시리즈 4편\n'마스터스 오브 디 에어'·'파친코'·'지하창고 사일로의 비밀'·'핀치'","link":"https://www.maxmovie.com/news/437213","retrieved":1711616865379,"image":"https://d3ihz389yobwks.cloudfront.net/1711605277185xW7av.jpg"},{"title":"곧 20만 '스파이 패밀리', '귀칼' 흥행 잇는다…애니 강세 계속","contents":"'귀칼' 50만명, '스파패' 20만명 눈앞\n올해도 美日 애니메이션 열풍","link":"https://www.maxmovie.com/news/437204","retrieved":1711631117088,"image":"https://d3ihz389yobwks.cloudfront.net/1711588918204upIup.jpg"},{"title":"'댓글부대', 34일간 1위 '파묘' 제치고 박스오피스 정상","contents":"27일 개봉, 12만7000여명 동원..박스오피스 1위\n'파묘', '괴물'과 같은 34일 연속 1위..2위로 하강","link":"https://www.maxmovie.com/news/437202","retrieved":1711631117090,"image":"https://d3ihz389yobwks.cloudfront.net/1711578126871SJGqD.jpg"},{"title":"[데일리 핫이슈] 전지현·강동원 '북극성' 촬영, 김새론 입장 두고 설왕설래, 안판석 표 멜로 등판","contents":"전날 일어난 엔터테인먼트 이슈를 소개합니다","link":"https://www.maxmovie.com/news/437201","retrieved":1711631117091,"image":"https://d3ihz389yobwks.cloudfront.net/1711530182233KzAEJ.jpg"},{"title":"세계 최초 청각장애인 아이돌 그룹 탄생..수어로 노래한다","contents":"'장애인의 날' 4월20일 정식 데뷔 \nH.O.T 대표곡 '빛' 리메이크 기대","link":"https://www.maxmovie.com/news/437198","retrieved":1711620469415,"image":"https://d3ihz389yobwks.cloudfront.net/1711527765795rioWM.jpg"},{"title":"영화 관람료 1만5000원 중 450원이 줄어든다?  그렇다면...","contents":"정부, 영화 관람료 3% 해당 부담금 폐지한다\n영화계 우려 \"한국영화 위기 타개 필요 재원\" \n극장 영화 관람료 인하 가능성? 얼마나 될까","link":"https://www.maxmovie.com/news/437197","retrieved":1711631117095,"image":"https://d3ihz389yobwks.cloudfront.net/1711526394168PHgRh.jpg"},{"title":"이승윤, 무대인사 나선다...관객들과 완벽한 '도킹' 예고","contents":"30·31일 '이승윤 콘서트 도킹:리프트오프' \n싱어롱 상영회, 포스터 증정 이벤트까지","link":"https://www.maxmovie.com/news/437196","retrieved":1711631117096,"image":"https://d3ihz389yobwks.cloudfront.net/1711525175125S36I3.jpg"},{"title":"'이혼' 황정음이 털어놓은 심경 \"개인적인 일로 피해, 죄송한 마음\"","contents":"이혼 소송 소식 알려진 후 첫 공식석상\n\"본연의 연기에만 온 열정으로 집중\"","link":"https://www.maxmovie.com/news/437195","retrieved":1711606150963,"image":"https://d3ihz389yobwks.cloudfront.net/1711521620817Qy8Z6.jpg"},{"title":"티아라 출신 아름, 극단적 선택 시도…치료 중","contents":"27일 오전 극단적 선택 시도로 입원\n\"의식 없는 상태\" 연락 자제 당부","link":"https://www.maxmovie.com/news/437194","retrieved":1711616865381,"image":"https://d3ihz389yobwks.cloudfront.net/1711518872947s4Fqj.jpg"},{"title":"벌써 채종협 그리워…종방한 '아이 러브 유' 결말은?","contents":"일드 '아이 러브 유' 3월26일 10회로 종방\n\"유리 태오 계속 보고 싶다\" 속편 제작 요청\n채종협, SNS 통해 종방 소감 및 감사 인사","link":"https://www.maxmovie.com/news/437192","retrieved":1711631117100,"image":"https://d3ihz389yobwks.cloudfront.net/1711516073379DY7Yg.jpg"},{"title":"전혜진, 시부상...고 이선균 비보 3개월만","contents":"소속사 \"27일 전혜진 시부상\" 이외 답변은 말 아껴\n지난해 세상 떠난 고 이선균, 유작 연내 개봉 준비","link":"https://www.maxmovie.com/news/437191","retrieved":1711631117104,"image":"https://d3ihz389yobwks.cloudfront.net/1711515000488XbS4H.jpg"},{"title":"'삼체' 전 세계적인 인기에 '원작' 중국도 들썩...불법 시청 지적도","contents":"중국 SF소설 각색, 문화대혁명 묘사 갑론을박\n넷플릭스 서비스 안 되는데..\"도둑 시청?\" 시선","link":"https://www.maxmovie.com/news/437188","retrieved":1711631117106,"image":"https://d3ihz389yobwks.cloudfront.net/1711501143805b14iG.jpg"},{"title":"음모 파헤치는 '댓글부대'냐, 땅에 서린 한 파내는 '파묘'냐","contents":"'댓글부대' 예매율 1위로 지각 변동 예고\n'파묘' 여전한 뒷심…한국영화 나란히 1~2위","link":"https://www.maxmovie.com/news/437190","retrieved":1711631117107,"image":"https://d3ihz389yobwks.cloudfront.net/1711504028523yBYTB.jpg"}]}