{"title":"맥스무비 ─ 기획","url":"https://www.maxmovie.com/plan","favicon":"https://www.maxmovie.com/favicon.ico","elements":[{"title":"현빈, 가수 김범수 뮤직비디오 출연한 까닭은?","contents":"김범수 신곡 '그대의 세계' 뮤비 주인공\n손예진과 결혼식 축가 김범수와의 인연","link":"https://www.maxmovie.com/news/436671","retrieved":1708568006077,"image":"https://d3ihz389yobwks.cloudfront.net/17085642677674hlQC.jpg"},{"title":"티모시 샬라메, 상금 100만원 받았을까...'유퀴즈' 방송은 언제?","contents":"'듄:파트2' 프로모션 젠데이아와 출연 \n영화 개봉일인 2월28일 방송 예정","link":"https://www.maxmovie.com/news/436668","retrieved":1708568006079,"image":"https://d3ihz389yobwks.cloudfront.net/1708562106297LPdR1.jpg"},{"title":"'서울의 봄' \"역사의 올바른 편에 선 이들에 바치는 헌사\"","contents":"미국 포브스 호평 \"격동의 사건 압축\"\n올해 미국 스트리밍 플랫폼에서 공개","link":"https://www.maxmovie.com/news/436667","retrieved":1708561848824,"image":"https://d3ihz389yobwks.cloudfront.net/1708558788135Jsg9H.jpg"},{"title":"[#Shorts] 티모시 샬라메의 '쓸데없는 걱정'... 순간 포착!","contents":"\"초콜릿 만들다 우주로, 혼란스러워 하지 않을까\"\n'웡카' 250만 관객 돌파, 2월28일 '듄:파트2' 개봉","link":"https://www.maxmovie.com/news/436666","retrieved":1708561848827,"image":"https://i.ytimg.com/vi/fHHfkfbKN0s/0.jpg"},{"title":"[#Shorts] 차원이 다른 '달달함' 티모시 샬라메의 K하트!","contents":"<span class=\"imgBox  floatLeft\"><a href=\"/news/436665\"><span class=\"imgBox\" style=\"background-image:url(https://i.ytimg.com/vi/Y5EyOr2T-FU/0.jpg);background-size:cover\"></span></a></span><span class=\"textBox floatLeft stickerKey1\"><a href=\"/news/436665\"><h4>[#Shorts] 차원이 다른 '달달함' 티모시 샬라메의 K하트!</h4></a><span>1시간 전<!-- --> · <a href=\"/writer/142\">조현주 기자</a></span></span>","link":"https://www.maxmovie.com/news/436665","retrieved":1708561848828,"image":"https://i.ytimg.com/vi/Y5EyOr2T-FU/0.jpg"},{"title":"'스탤론 패밀리'가 돌아온다..실베스터 스탤론 가족의 좌충우돌","contents":"파라마운트+ 오리지널 시리즈 22일 공개\n스탤론 부부와 세 딸의 사실적 일상 화제","link":"https://www.maxmovie.com/news/436664","retrieved":1708561848830,"image":"https://d3ihz389yobwks.cloudfront.net/1708557426432aZRLo.jpg"},{"title":"'패스트 라이브즈'와 '성난 사람들', 미 작가조합상 후보 지명","contents":"각각 영화와 TV 리미티드 시리즈 부문\n미국 유수 시상식 휩쓸며 한국계 활약","link":"https://www.maxmovie.com/news/436663","retrieved":1708556872993,"image":"https://d3ihz389yobwks.cloudfront.net/1708554624428cO1Z7.jpg"},{"title":"[#Shorts]  한국어로 '듄친자' 발음하고 뿌듯해하는 티모시 샬라메 보실 분?","contents":"2월28일 '듄:파트2' 개봉 앞두고 내한해\n'듄친자' 이유? \"드니 빌뇌브 감독 덕분\"","link":"https://www.maxmovie.com/news/436662","retrieved":1708506538701,"image":"https://i.ytimg.com/vi/HUDlz7FRlCw/0.jpg"},{"title":"질문 쏟아져 취재진 명함 추첨까지…티모시·'듄2' 인기 실감한 기자회견","contents":"\"'듄'의 인기는 빌뇌브 감독 덕분\"\n'듄친자' 한국어 발음에 'K하트'도","link":"https://www.maxmovie.com/news/436661","retrieved":1708506538701,"image":"https://i.ytimg.com/vi/HUDlz7FRlCw/0.jpg"},{"title":"'패스트 라이브즈' 셀린 송, 또 하나의 트로피..코닥필름어워즈 수상","contents":"<span class=\"imgBox  floatLeft\"><a href=\"/news/436660\"><span class=\"imgBox\" style=\"background-image:url(https://d3ihz389yobwks.cloudfront.net/17084994852545fzP2.jpg);background-size:cover\"></span></a></span><span class=\"textBox floatLeft stickerKey1\"><a href=\"/news/436660\"><h4>'패스트 라이브즈' 셀린 송, 또 하나의 트로피..코닥필름어워즈 수상</h4></a><span>18시간 전<!-- --> · <a href=\"/writer/134\">윤여수 기자</a></span></span>","link":"https://www.maxmovie.com/news/436660","retrieved":1708503009601,"image":"https://d3ihz389yobwks.cloudfront.net/17084994852545fzP2.jpg"}]}